proyecto principal/I2C/CONTROL.v
module CONTROL_I2C (

    input wire clk,
    input wire rst,
    input wire start,
    input wire rw,
    input wire scl_rise,
    input wire scl_fall,
    input wire z_bits,
    input wire z_bytes,
    input wire sda_in,

    output reg scl_enable,
    output reg drive_sel,
    output reg drive_low_fsm,
    output reg load_shift,
    output reg shift_tx,
    output reg shift_rx,
    output reg store_rx,
    output reg load_bit_counter,
    output reg dec_bit_counter,
    output reg load_byte_counter,
    output reg dec_byte_counter,
    output reg busy,
    output reg done,
    output reg ack_error,
    output reg byte_done
);

    // DEFINICIÓN DE ESTADOS
    parameter S_IDLE      = 8'b00000001; 
    parameter S_START     = 8'b00000010; 
    parameter S_TX_DATA   = 8'b00000100; 
    parameter S_RX_ACK    = 8'b00001000; 
    parameter S_RX_DATA   = 8'b00010000; 
    parameter S_TX_ACK    = 8'b00100000; 
    parameter S_BYTE_DONE = 8'b01000000; 
    parameter S_STOP      = 8'b10000000; 

    reg [7:0] NEXT_STATE;

    // MAQUINA DE ESTADOS
    always @(posedge clk or posedge rst) begin

        if (rst) begin
            NEXT_STATE = S_IDLE;
            ack_error  = 0;
        
        end else begin
            case (NEXT_STATE)

                S_IDLE: begin
                    ack_error = 0;
                    if (start) NEXT_STATE = S_START;
                    else       NEXT_STATE = S_IDLE;
                end

                S_START: begin
                    if (scl_fall) NEXT_STATE = S_TX_DATA;
                    else          NEXT_STATE = S_START;
                end

                S_TX_DATA: begin
                    if (scl_fall && z_bits) NEXT_STATE = S_RX_ACK;
                    else                    NEXT_STATE = S_TX_DATA;
                end

                S_RX_ACK: begin
                    if (scl_rise && sda_in) ack_error = 1;
                    if (scl_fall)           NEXT_STATE = S_BYTE_DONE;
                    else                    NEXT_STATE = S_RX_ACK;
                end

                S_RX_DATA: begin
                    if (scl_fall && z_bits) NEXT_STATE = S_TX_ACK;
                    else                    NEXT_STATE = S_RX_DATA;
                end

                S_TX_ACK: begin
                    if (scl_fall) NEXT_STATE = S_BYTE_DONE;
                    else          NEXT_STATE = S_TX_ACK;
                end

                S_BYTE_DONE: begin
                    if (ack_error)    NEXT_STATE = S_STOP;
                    else if (z_bytes) NEXT_STATE = S_STOP;
                    else begin
                        if (rw) NEXT_STATE = S_RX_DATA;
                        else    NEXT_STATE = S_TX_DATA;
                    end
                end

                S_STOP: begin
                    if (scl_rise) NEXT_STATE = S_IDLE;
                    else          NEXT_STATE = S_STOP;
                end

                default: NEXT_STATE = S_IDLE;

            endcase
        end
    end

    // LOGICA DE SALIDAS
    always @(*) begin
        case (NEXT_STATE)

            S_IDLE: begin
                scl_enable    = 0; load_bit_counter  = 0;
                drive_sel     = 1; dec_bit_counter   = 0;
                drive_low_fsm = 0; load_byte_counter = 0;
                load_shift    = 0; dec_byte_counter  = 0;
                shift_tx      = 0; busy              = 0;
                shift_rx      = 0; done              = 0;
                store_rx      = 0; byte_done         = 0;
            end

            S_START: begin
                scl_enable    = 1; load_bit_counter  = 1;
                drive_sel     = 1; dec_bit_counter   = 0;
                drive_low_fsm = 1; load_byte_counter = 1;
                load_shift    = 1; dec_byte_counter  = 0;
                shift_tx      = 0; busy              = 1;
                shift_rx      = 0; done              = 0;
                store_rx      = 0; byte_done         = 0;
            end

            S_TX_DATA: begin
                scl_enable    = 1;        load_bit_counter  = 0;   
                drive_sel     = 0;        dec_bit_counter   = scl_fall;   
                drive_low_fsm = 0;        load_byte_counter = 0;   
                load_shift    = 0;        dec_byte_counter  = 0;   
                shift_tx      = scl_fall; busy              = 1;           
                shift_rx      = 0;        done              = 0;   
                store_rx      = 0;        byte_done         = 0;   
            end

            S_RX_ACK: begin
                scl_enable    = 1; load_bit_counter  = 0;
                drive_sel     = 1; dec_bit_counter   = 0;
                drive_low_fsm = 0; load_byte_counter = 0;
                load_shift    = 0; dec_byte_counter  = scl_fall;
                shift_tx      = 0; busy              = 1;
                shift_rx      = 0; done              = 0;
                store_rx      = 0; byte_done         = 0;
            end

            S_RX_DATA: begin
                scl_enable    = 1;        load_bit_counter  = 0;
                drive_sel     = 1;        dec_bit_counter   = scl_fall;            
                drive_low_fsm = 0;        load_byte_counter = 0;            
                load_shift    = 0;        dec_byte_counter  = 0;            
                shift_tx      = 0;        busy              = 1;            
                shift_rx      = scl_rise; done              = 0;                    
                store_rx      = 0;        byte_done         = 0;
            end

            S_TX_ACK: begin
                scl_enable    = 1;                       load_bit_counter  = 0;
                drive_sel     = 1;                       dec_bit_counter   = 0;
                drive_low_fsm = (z_bytes) ? 1'b0 : 1'b1; load_byte_counter = 0;                        
                load_shift    = 0;                       dec_byte_counter  = scl_fall;
                shift_tx      = 0;                       busy              = 1;
                shift_rx      = 0;                       done              = 0;
                store_rx      = scl_rise;                byte_done         = 0;        
            end

            S_BYTE_DONE: begin
                scl_enable    = 1;                 load_bit_counter  = 1;
                drive_sel     = 1;                 dec_bit_counter   = 0;
                drive_low_fsm = 1;                 load_byte_counter = 0;
                load_shift    = (~z_bytes && ~rw); dec_byte_counter  = 0;                
                shift_tx      = 0;                 busy              = 1;
                shift_rx      = 0;                 done              = 0;
                store_rx      = 0;                 byte_done         = 1;
            end

            S_STOP: begin
                scl_enable    = 1;                        load_bit_counter  = 0;
                drive_sel     = 1;                        dec_bit_counter   = 0;
                drive_low_fsm = (scl_rise) ? 1'b0 : 1'b1; load_byte_counter = 0;                        
                load_shift    = 0;                        dec_byte_counter  = 0;
                shift_tx      = 0;                        busy              = 1;
                shift_rx      = 0;                        done              = scl_rise;
                store_rx      = 0;                        byte_done         = 0;
            end

            default: begin
                scl_enable    = 0; load_bit_counter  = 0;
                drive_sel     = 0; dec_bit_counter   = 0;
                drive_low_fsm = 0; load_byte_counter = 0;
                load_shift    = 0; dec_byte_counter  = 0;
                shift_tx      = 0; busy              = 0;
                shift_rx      = 0; done              = 0;
                store_rx      = 0; byte_done         = 0;
            end

        endcase
    end

endmodule

proyecto principal/controlador ads1115/I2C/CONTADOR_BYTES.v
module CONTADOR_BYTES(
    input  wire clk,
    input  wire rst,
    input  wire load,
    input  wire dec,
    input  wire [7:0] num_bytes,

    output wire z_bytes,
    output wire [7:0] value
);
    reg [7:0] count;

    always @(posedge clk or posedge rst) begin
        if (rst)
            count <= 8'd0;

        else if (load)
            count <= num_bytes;

        else if (dec && (count != 8'd0))
            count <= count - 8'd1;
    end

    assign z_bytes = (count == 8'd0);
    assign value   = count;
    
endmodule

proyecto principal/I2C/CONTADOR_BITS.v
module CONTADOR_BITS(
    input  wire clk,
    input  wire rst,
    input  wire load,
    input  wire dec,

    output wire z_bits,
    output wire [2:0] value
);

    reg [2:0] count;

    always @(posedge clk or posedge rst) begin

        if (rst)
            count <= 3'd0;

        else if (load)
            count <= 3'd7;

        else if (dec && (count != 3'd0))
            count <= count - 3'd1;
    end

    assign z_bits = (count == 3'd0);
    assign value  = count;

endmodule

proyecto principal/I2C/SHIFT_REG.v
module SHIFT_REGISTER(
    input  wire       clk,
    input  wire       rst,
    input  wire       load,
    input  wire       shift_tx,
    input  wire       shift_rx,
    input  wire       store_rx,
    input  wire [7:0] tx_byte,
    input  wire       sda_in,

    output wire       tx_bit,
    output wire [7:0] rx_data
);

    reg [7:0] shift_reg;
    reg [7:0] rx_reg;

    // Control del registro de desplazamiento (shift_reg)
    always @(posedge clk or posedge rst) begin
        if (rst) begin
            shift_reg <= 8'd0;

        end else if (load) begin
            shift_reg <= tx_byte;

        end else if (shift_tx) begin
            shift_reg <= {shift_reg[6:0], 1'b0};     

        end else if (shift_rx) begin
            shift_reg <= {shift_reg[6:0], sda_in};            
        end
    end

    always @(posedge clk or posedge rst) begin
        if (rst) begin
            rx_reg <= 8'd0;

        end else if (store_rx) begin
            rx_reg <= shift_reg;
        end
    end

    assign tx_bit  = shift_reg[7];
    assign rx_data = rx_reg;

endmodule

proyecto principal/I2C/I2C_CLOCK_GENERATOR.v
module I2C_CLOCK_GENERATOR #(
    parameter CLK_FREQ_HZ = 25_000_000,
    parameter I2C_FREQ_HZ = 100_000
)(
    input  wire clk,
    input  wire rst,
    input  wire enable,

    output reg  scl,
    output reg  scl_rise,
    output reg  scl_fall
);

    // Cálculo del número de ciclos de reloj por cada semiciclo I2C
    localparam HALF_PERIOD = CLK_FREQ_HZ / (2 * I2C_FREQ_HZ);    
    // Calcula automáticamente los bits necesarios para el contador
    localparam COUNTER_WIDTH = $clog2(HALF_PERIOD);

    reg [COUNTER_WIDTH-1:0] counter;

    always @(posedge clk or posedge rst) begin
        if (rst) begin
            counter  <= 0;
            scl      <= 1'b1; 
            scl_rise <= 1'b0;
            scl_fall <= 1'b0;
            
        end else if (!enable) begin
            counter  <= 0;
            scl      <= 1'b1; 
            scl_rise <= 1'b0;
            scl_fall <= 1'b0;
            
        end else if (counter == HALF_PERIOD - 1) begin
            counter  <= 0;
            scl      <= ~scl;     
            scl_rise <= ~scl;     
            scl_fall <= scl;      
            
        end else begin
            counter  <= counter + 1'b1;
            scl_rise <= 1'b0;
            scl_fall <= 1'b0;
        end
    end

endmodule

proyecto principal/I2C/Top_I2C.v
module TOP_I2C #(
    parameter CLK_FREQ_HZ = 25_000_000,
    parameter I2C_FREQ_HZ = 100_000
)(
    input  wire clk,
    input  wire rst,
    input  wire start,
    input  wire rw,
    input  wire [7:0] tx_byte,
    input  wire [7:0] num_bytes,

    output wire [7:0] rx_data,
    output wire busy,
    output wire done,
    output wire ack_error,
    output wire byte_done,

    inout  wire SDA,
    output wire SCL
);

    wire scl_enable;
    wire scl_rise;
    wire scl_fall;

    wire drive_sel;
    wire drive_low_fsm;
    wire drive_low;

    wire sda_in;
    wire tx_bit;

    wire load_shift;
    wire shift_tx;
    wire shift_rx;
    wire store_rx;

    wire load_bit_counter;
    wire dec_bit_counter;
    wire z_bits;

    wire load_byte_counter;
    wire dec_byte_counter;
    wire z_bytes;

    wire [2:0] bit_value;
    wire [7:0] byte_value;

    // I2C utiliza salidas Open-Drain: drive_low = 1 -> fuerza un '0' drive_low = 0 -> alta impedancia
    assign SDA = drive_low ? 1'b0 : 1'bz;
    assign sda_in = SDA;
    assign drive_low = (drive_sel) ? drive_low_fsm : ~tx_bit;


    I2C_CLOCK_GENERATOR #(
        .CLK_FREQ_HZ(CLK_FREQ_HZ),
        .I2C_FREQ_HZ(I2C_FREQ_HZ)
    )
    CLOCK_GEN(
        .clk      (clk),
        .rst      (rst),
        .enable   (scl_enable),
        .scl      (SCL),
        .scl_rise (scl_rise),
        .scl_fall (scl_fall)
    );


    SHIFT_REGISTER SHIFT(
        .clk      (clk),
        .rst      (rst),
        .load     (load_shift),
        .shift_tx (shift_tx),
        .shift_rx (shift_rx),
        .store_rx (store_rx),
        .tx_byte  (tx_byte),
        .sda_in   (sda_in),
        .tx_bit   (tx_bit),
        .rx_data  (rx_data)
    );

    CONTADOR_BITS BIT_COUNTER(
        .clk    (clk),
        .rst    (rst),
        .load   (load_bit_counter),
        .dec    (dec_bit_counter),
        .z_bits (z_bits),
        .value  (bit_value)
    );

    CONTADOR_BYTES BYTE_COUNTER(
        .clk       (clk),
        .rst       (rst),
        .load      (load_byte_counter),
        .dec       (dec_byte_counter),
        .num_bytes (num_bytes),
        .z_bytes   (z_bytes),
        .value     (byte_value)
    );

    CONTROL_I2C CONTROL (
        .clk      (clk),
        .rst      (rst),
        .start    (start),
        .rw       (rw),
        .scl_rise (scl_rise),
        .scl_fall (scl_fall),
        .z_bits   (z_bits),
        .z_bytes  (z_bytes),
        .sda_in   (sda_in),
        
        .scl_enable    (scl_enable),
        .drive_sel     (drive_sel),
        .drive_low_fsm (drive_low_fsm),
        .load_shift    (load_shift),
        .shift_tx      (shift_tx),
        .shift_rx      (shift_rx),
        .store_rx      (store_rx),
        
        .load_bit_counter  (load_bit_counter),
        .dec_bit_counter   (dec_bit_counter),
        .load_byte_counter (load_byte_counter),
        .dec_byte_counter  (dec_byte_counter),
        
        .busy      (busy),
        .done      (done),
        .ack_error (ack_error),
        .byte_done (byte_done)
    );

endmodule

proyecto principal/I2C/TESTBENCH.v
`timescale 1ns / 1ps

module tb_TOP_I2C;

    localparam CLK_FREQ_HZ = 10_000_000;
    localparam I2C_FREQ_HZ = 1_000_000;
    localparam CLK_PERIOD  = 100; // 100ns

    reg        clk;
    reg        rst;
    reg        start;
    reg        rw;
    reg  [7:0] tx_byte;
    reg  [7:0] num_bytes;

    wire [7:0] rx_data;
    wire       busy;
    wire       done;
    wire       ack_error;
    wire       byte_done;

    tri1       SDA;
    wire       SCL;

    reg        slave_drive_low;
    reg  [7:0] bytes_enviados_master;
    reg  [7:0] bytes_recibidos_master;

    // Resistencias Pull-Up del bus
    assign SDA = slave_drive_low ? 1'b0 : 1'bz;

    pullup(SDA);

    // Instanciación de la Unidad Bajo Prueba (UUT)
    TOP_I2C #(
        .CLK_FREQ_HZ(CLK_FREQ_HZ),
        .I2C_FREQ_HZ(I2C_FREQ_HZ)
    ) uut (
        .clk(clk),
        .rst(rst),
        .start(start),
        .rw(rw),
        .tx_byte(tx_byte),
        .num_bytes(num_bytes),
        .rx_data(rx_data),
        .busy(busy),
        .done(done),
        .ack_error(ack_error),
        .byte_done(byte_done),
        .SDA(SDA),
        .SCL(SCL)
    );

    // Generador de Reloj del Sistema
    always #(CLK_PERIOD/2) clk = ~clk;

    task aplicar_reset;
        begin
            rst = 1; start = 0; rw = 0;
            tx_byte = 8'h00; num_bytes = 8'd0;
            slave_drive_low = 0;
            bytes_enviados_master = 0; bytes_recibidos_master = 0;
            #(CLK_PERIOD * 5);
            rst = 0;
            #(CLK_PERIOD * 2);
        end
    endtask

    // Modelo del Esclavo Emulado 

    integer bit_cnt;
    reg [7:0] frame_idx;
    reg [7:0] data_to_master;
    reg [7:0] shift_reg_esclavo;
    reg       slave_rw; // El esclavo guarda la dirección de flujo de forma autónoma

    // Reset de la transacción
    always @(posedge start or posedge rst) begin
        bit_cnt         <= 0;
        frame_idx       <= 0;
        slave_drive_low <= 0;
        slave_rw        <= 0;
    end

    // Muestreo de Datos Seguro: Siempre en el flanco de SUBIDA (SCL Alto = Dato Estable)
    always @(posedge SCL) begin
        if (busy) begin
            if (bit_cnt < 8) begin
                if (frame_idx == 0 || slave_rw == 0) begin
                    shift_reg_esclavo <= {shift_reg_esclavo[6:0], SDA};
                end
            end
            bit_cnt <= bit_cnt + 1;
        end
    end

    // Control del Bus y Respuestas: En el flanco de BAJADA (SCL Bajo = Permitido cambiar SDA)
    always @(negedge SCL) begin
        if (busy) begin
            if (bit_cnt == 8) begin
                // Fin del ciclo de transmisión de datos, flanco previo al ACK (9no pulso)
                if (frame_idx == 0) begin : FRAME_DIRECCION
                    slave_drive_low <= 1; // Responder con ACK
                    slave_rw        <= shift_reg_esclavo[0]; // El bit de dirección real (Bit 0)
                    $display("[TB - Esclavo] Direccion detectada: 0x%h. Modo seteado por Bus: %s", shift_reg_esclavo, shift_reg_esclavo[0] ? "LECTURA" : "ESCRITURA");
                end
                else if (slave_rw == 0) begin : FRAME_ESCRITURA
                    slave_drive_low <= 1; // Responder con ACK al maestro
                    $display("[TB - Esclavo] Recibido byte %0d del Maestro (Valor: 0x%h). Respondiendo con ACK.", bytes_enviados_master + 1, shift_reg_esclavo);
                end
                else begin : FRAME_LECTURA_ACK
                    slave_drive_low <= 0; // El maestro controla el ACK en modo lectura
                end
            end 
            else if (bit_cnt == 9) begin
                // Fin del ciclo de ACK, pasamos al siguiente frame
                bit_cnt         <= 0;
                frame_idx       <= frame_idx + 1;
                
                if (slave_rw == 1) begin
                    data_to_master = (frame_idx + 1 == 1) ? 8'hAB : 8'hCD;
                    slave_drive_low <= ~data_to_master[7];
                end else begin
                    slave_drive_low <= 0;
                end
            end
            else begin
                // Transmisión de los bits restantes (Bit 6 al Bit 0) en modo lectura
                if (slave_rw == 1 && frame_idx > 0) begin
                    if (bit_cnt < 8) begin
                        data_to_master = (frame_idx == 1) ? 8'hAB : 8'hCD;
                        slave_drive_low <= ~data_to_master[7 - bit_cnt];
                    end
                end else begin
                    slave_drive_low <= 0;
                end
            end
        end
    end

    // Contadores estadísticos del Testbench (Ajustado a bit_cnt == 8 debido al nuevo muestreo)
    always @(negedge SCL) begin
        if (busy && bit_cnt == 8) begin
            if (frame_idx != 0) begin
                if (slave_rw == 0) bytes_enviados_master   <= bytes_enviados_master + 1;
                else               bytes_recibidos_master  <= bytes_recibidos_master + 1;
            end
        end
    end

    // Estímulos de Prueba

    initial begin
        $dumpfile("tb_TOP_I2C.vcd");
        $dumpvars(0, tb_TOP_I2C);

        clk = 0;
        aplicar_reset();

        // PRUEBA 1: ESCRITURA DE 2 BYTES DE DATOS

        $display("\n--- Iniciando Transaccion de Escritura (2 Bytes de Datos) ---");

        num_bytes = 8'd3;      // Exactamente 2 bytes de datos
        rw        = 1'b0;      // Operación de escritura
        tx_byte   = 8'h3E;     // Byte de dirección (Bit 0 en '0' para escritura)
        start     = 1'b1;
        #(CLK_PERIOD);
        start     = 1'b0;

        @(posedge byte_done);  
        #(CLK_PERIOD / 4);     // Retardo de seguridad para evitar condiciones de carrera (Setup Time)
        tx_byte   = 8'h11;     
        $display("[TB] Direccion procesada de forma segura. Cargando dato 1: 0x11");

        @(posedge byte_done);  
        #(CLK_PERIOD / 4);     
        tx_byte   = 8'hA5;     
        $display("[TB] Dato 1 procesado de forma segura. Cargando dato 2: 0xA5");

        @(posedge done);
        $display("[TB] Transaccion de Escritura Finalizada de forma exitosa.");
        #(CLK_PERIOD * 20);

        // PRUEBA 2: LECTURA DE 2 BYTES DE DATOS

        $display("\n--- Iniciando Transaccion de Lectura (2 Bytes de Datos) ---");
        bytes_recibidos_master = 0;

        num_bytes = 8'd3;      // Se esperan exactamente 2 bytes
        rw        = 1'b1;      // Operación de lectura
        tx_byte   = 8'h3F;     // Byte de dirección (Bit 0 en '1' para lectura)
        start     = 1'b1;
        #(CLK_PERIOD);
        start     = 1'b0;

        @(posedge byte_done);  
        $display("[TB] Direccion de lectura validada.");

        @(posedge byte_done);  
        $display("[TB] Maestro capto el 1er Byte. Valor: 0x%H (Esperado: 0xAB)", rx_data);

        // El segundo byte provocará la activación de done directo debido al fin del conteo.
        @(posedge done);
        $display("[TB] Maestro capto el 2do Byte. Valor: 0x%H (Esperado: 0xCD)", rx_data);
        $display("[TB] Transaccion de Lectura Finalizada.");

        #(CLK_PERIOD * 20);
        $display("\n--- Todas las pruebas terminaron satisfactoriamente ---");
        $finish;
    end

endmodule

proyecto principal/I2C/tb_TOP_I2C.vcd
$date
	Sun Jul  5 13:44:07 2026
$end
$version
	Icarus Verilog
$end
$timescale
	1ps
$end
$scope module tb_TOP_I2C $end
$var wire 1 ! SDA $end
$var wire 8 " rx_data [7:0] $end
$var wire 1 # done $end
$var wire 1 $ byte_done $end
$var wire 1 % busy $end
$var wire 1 & ack_error $end
$var wire 1 ' SCL $end
$var parameter 32 ( CLK_FREQ_HZ $end
$var parameter 32 ) CLK_PERIOD $end
$var parameter 32 * I2C_FREQ_HZ $end
$var reg 8 + bytes_enviados_master [7:0] $end
$var reg 8 , bytes_recibidos_master [7:0] $end
$var reg 1 - clk $end
$var reg 8 . data_to_master [7:0] $end
$var reg 8 / frame_idx [7:0] $end
$var reg 8 0 num_bytes [7:0] $end
$var reg 1 1 rst $end
$var reg 1 2 rw $end
$var reg 8 3 shift_reg_esclavo [7:0] $end
$var reg 1 4 slave_drive_low $end
$var reg 1 5 slave_rw $end
$var reg 1 6 start $end
$var reg 8 7 tx_byte [7:0] $end
$var integer 32 8 bit_cnt [31:0] $end
$scope module uut $end
$var wire 1 ! SDA $end
$var wire 1 - clk $end
$var wire 8 9 num_bytes [7:0] $end
$var wire 1 1 rst $end
$var wire 1 2 rw $end
$var wire 1 : sda_in $end
$var wire 1 6 start $end
$var wire 8 ; tx_byte [7:0] $end
$var wire 1 < z_bytes $end
$var wire 1 = z_bits $end
$var wire 1 > tx_bit $end
$var wire 1 ? store_rx $end
$var wire 1 @ shift_tx $end
$var wire 1 A shift_rx $end
$var wire 1 B scl_rise $end
$var wire 1 C scl_fall $end
$var wire 1 D scl_enable $end
$var wire 8 E rx_data [7:0] $end
$var wire 1 F load_shift $end
$var wire 1 G load_byte_counter $end
$var wire 1 H load_bit_counter $end
$var wire 1 I drive_sel $end
$var wire 1 J drive_low_fsm $end
$var wire 1 K drive_low $end
$var wire 1 # done $end
$var wire 1 L dec_byte_counter $end
$var wire 1 M dec_bit_counter $end
$var wire 8 N byte_value [7:0] $end
$var wire 1 $ byte_done $end
$var wire 1 % busy $end
$var wire 3 O bit_value [2:0] $end
$var wire 1 & ack_error $end
$var wire 1 ' SCL $end
$var parameter 32 P CLK_FREQ_HZ $end
$var parameter 32 Q I2C_FREQ_HZ $end
$scope module BIT_COUNTER $end
$var wire 1 - clk $end
$var wire 1 1 rst $end
$var wire 3 R value [2:0] $end
$var wire 1 = z_bits $end
$var wire 1 H load $end
$var wire 1 M dec $end
$var reg 3 S count [2:0] $end
$upscope $end
$scope module BYTE_COUNTER $end
$var wire 1 - clk $end
$var wire 8 T num_bytes [7:0] $end
$var wire 1 1 rst $end
$var wire 8 U value [7:0] $end
$var wire 1 < z_bytes $end
$var wire 1 G load $end
$var wire 1 L dec $end
$var reg 8 V count [7:0] $end
$upscope $end
$scope module CLOCK_GEN $end
$var wire 1 - clk $end
$var wire 1 1 rst $end
$var wire 1 D enable $end
$var parameter 32 W CLK_FREQ_HZ $end
$var parameter 32 X COUNTER_WIDTH $end
$var parameter 64 Y HALF_PERIOD $end
$var parameter 32 Z I2C_FREQ_HZ $end
$var reg 3 [ counter [2:0] $end
$var reg 1 ' scl $end
$var reg 1 C scl_fall $end
$var reg 1 B scl_rise $end
$upscope $end
$scope module CONTROL $end
$var wire 1 - clk $end
$var wire 1 1 rst $end
$var wire 1 2 rw $end
$var wire 1 C scl_fall $end
$var wire 1 B scl_rise $end
$var wire 1 : sda_in $end
$var wire 1 6 start $end
$var wire 1 = z_bits $end
$var wire 1 < z_bytes $end
$var parameter 8 \ S_BYTE_DONE $end
$var parameter 8 ] S_IDLE $end
$var parameter 8 ^ S_RX_ACK $end
$var parameter 8 _ S_RX_DATA $end
$var parameter 8 ` S_START $end
$var parameter 8 a S_STOP $end
$var parameter 8 b S_TX_ACK $end
$var parameter 8 c S_TX_DATA $end
$var reg 8 d NEXT_STATE [7:0] $end
$var reg 1 & ack_error $end
$var reg 1 % busy $end
$var reg 1 $ byte_done $end
$var reg 1 M dec_bit_counter $end
$var reg 1 L dec_byte_counter $end
$var reg 1 # done $end
$var reg 1 J drive_low_fsm $end
$var reg 1 I drive_sel $end
$var reg 1 H load_bit_counter $end
$var reg 1 G load_byte_counter $end
$var reg 1 F load_shift $end
$var reg 1 D scl_enable $end
$var reg 1 A shift_rx $end
$var reg 1 @ shift_tx $end
$var reg 1 ? store_rx $end
$upscope $end
$scope module SHIFT $end
$var wire 1 - clk $end
$var wire 1 F load $end
$var wire 1 1 rst $end
$var wire 8 e rx_data [7:0] $end
$var wire 1 : sda_in $end
$var wire 1 A shift_rx $end
$var wire 1 @ shift_tx $end
$var wire 1 ? store_rx $end
$var wire 8 f tx_byte [7:0] $end
$var wire 1 > tx_bit $end
$var reg 8 g rx_reg [7:0] $end
$var reg 8 h shift_reg [7:0] $end
$upscope $end
$upscope $end
$scope begin FRAME_DIRECCION $end
$upscope $end
$scope begin FRAME_ESCRITURA $end
$upscope $end
$scope begin FRAME_LECTURA_ACK $end
$upscope $end
$scope task aplicar_reset $end
$upscope $end
$upscope $end
$enddefinitions $end
$comment Show the parameter values. $end
$dumpall
b100 c
b100000 b
b10000000 a
b10 `
b10000 _
b1000 ^
b1 ]
b1000000 \
b11110100001001000000 Z
b101 Y
b11 X
b100110001001011010000000 W
b11110100001001000000 Q
b100110001001011010000000 P
b11110100001001000000 *
b1100100 )
b100110001001011010000000 (
$end
#0
$dumpvars
b0 h
b0 g
b0 f
b0 e
b1 d
b0 [
b0 V
b0 U
b0 T
b0 S
b0 R
b0 O
b0 N
0M
0L
0K
0J
1I
0H
0G
0F
b0 E
0D
0C
0B
0A
0@
0?
0>
1=
1<
b0 ;
1:
b0 9
b0 8
b0 7
06
05
04
bx 3
02
11
b0 0
b0 /
bx .
0-
b0 ,
b0 +
1'
0&
0%
0$
0#
b0 "
1!
$end
#50000
1-
#100000
0-
#150000
1-
#200000
0-
#250000
1-
#300000
0-
#350000
1-
#400000
0-
#450000
1-
#500000
0-
01
#550000
1-
#600000
0-
#650000
1-
#700000
0-
16
b111110 7
b111110 ;
b111110 f
b11 0
b11 9
b11 T
#750000
0:
0!
1K
1%
1F
1G
1J
1H
1D
b10 d
1-
#800000
0-
06
#850000
0<
b11 N
b11 U
b11 V
0=
b111 O
b111 R
b111 S
b111110 h
b1 [
1-
#900000
0-
#950000
b10 [
1-
#1000000
0-
#1050000
b11 [
1-
#1100000
0-
#1150000
b100 [
1-
#1200000
0-
#1250000
1C
0'
b0 [
1-
#1300000
0-
#1350000
0C
b1 [
0@
0F
0G
0J
0M
0I
0H
b100 d
1-
#1400000
0-
#1450000
b10 [
1-
#1500000
0-
#1550000
b11 [
1-
#1600000
0-
#1650000
b100 [
1-
#1700000
0-
#1750000
b1 8
bx0 3
1B
1'
b0 [
1-
#1800000
0-
#1850000
0B
b1 [
1-
#1900000
0-
#1950000
b10 [
1-
#2000000
0-
#2050000
b11 [
1-
#2100000
0-
#2150000
b100 [
1-
#2200000
0-
#2250000
1@
1M
1C
0'
b0 [
1-
#2300000
0-
#2350000
0@
0M
0C
b1 [
b1111100 h
b110 O
b110 R
b110 S
1-
#2400000
0-
#2450000
b10 [
1-
#2500000
0-
#2550000
b11 [
1-
#2600000
0-
#2650000
b100 [
1-
#2700000
0-
#2750000
b10 8
bx00 3
1B
1'
b0 [
1-
#2800000
0-
#2850000
0B
b1 [
1-
#2900000
0-
#2950000
b10 [
1-
#3000000
0-
#3050000
b11 [
1-
#3100000
0-
#3150000
b100 [
1-
#3200000
0-
#3250000
1@
1M
1C
0'
b0 [
1-
#3300000
0-
#3350000
1:
1!
0K
0@
0M
1>
0C
b1 [
b11111000 h
b101 O
b101 R
b101 S
1-
#3400000
0-
#3450000
b10 [
1-
#3500000
0-
#3550000
b11 [
1-
#3600000
0-
#3650000
b100 [
1-
#3700000
0-
#3750000
b11 8
bx001 3
1B
1'
b0 [
1-
#3800000
0-
#3850000
0B
b1 [
1-
#3900000
0-
#3950000
b10 [
1-
#4000000
0-
#4050000
b11 [
1-
#4100000
0-
#4150000
b100 [
1-
#4200000
0-
#4250000
1@
1M
1C
0'
b0 [
1-
#4300000
0-
#4350000
0@
0M
0C
b1 [
b11110000 h
b100 O
b100 R
b100 S
1-
#4400000
0-
#4450000
b10 [
1-
#4500000
0-
#4550000
b11 [
1-
#4600000
0-
#4650000
b100 [
1-
#4700000
0-
#4750000
b100 8
bx0011 3
1B
1'
b0 [
1-
#4800000
0-
#4850000
0B
b1 [
1-
#4900000
0-
#4950000
b10 [
1-
#5000000
0-
#5050000
b11 [
1-
#5100000
0-
#5150000
b100 [
1-
#5200000
0-
#5250000
1@
1M
1C
0'
b0 [
1-
#5300000
0-
#5350000
0@
0M
0C
b1 [
b11100000 h
b11 O
b11 R
b11 S
1-
#5400000
0-
#5450000
b10 [
1-
#5500000
0-
#5550000
b11 [
1-
#5600000
0-
#5650000
b100 [
1-
#5700000
0-
#5750000
b101 8
bx00111 3
1B
1'
b0 [
1-
#5800000
0-
#5850000
0B
b1 [
1-
#5900000
0-
#5950000
b10 [
1-
#6000000
0-
#6050000
b11 [
1-
#6100000
0-
#6150000
b100 [
1-
#6200000
0-
#6250000
1@
1M
1C
0'
b0 [
1-
#6300000
0-
#6350000
0@
0M
0C
b1 [
b11000000 h
b10 O
b10 R
b10 S
1-
#6400000
0-
#6450000
b10 [
1-
#6500000
0-
#6550000
b11 [
1-
#6600000
0-
#6650000
b100 [
1-
#6700000
0-
#6750000
b110 8
bx001111 3
1B
1'
b0 [
1-
#6800000
0-
#6850000
0B
b1 [
1-
#6900000
0-
#6950000
b10 [
1-
#7000000
0-
#7050000
b11 [
1-
#7100000
0-
#7150000
b100 [
1-
#7200000
0-
#7250000
1@
1M
1C
0'
b0 [
1-
#7300000
0-
#7350000
0@
0M
0C
b1 [
b10000000 h
b1 O
b1 R
b1 S
1-
#7400000
0-
#7450000
b10 [
1-
#7500000
0-
#7550000
b11 [
1-
#7600000
0-
#7650000
b100 [
1-
#7700000
0-
#7750000
b111 8
bx0011111 3
1B
1'
b0 [
1-
#7800000
0-
#7850000
0B
b1 [
1-
#7900000
0-
#7950000
b10 [
1-
#8000000
0-
#8050000
b11 [
1-
#8100000
0-
#8150000
b100 [
1-
#8200000
0-
#8250000
1@
1M
1C
0'
b0 [
1-
#8300000
0-
#8350000
0:
0!
1K
0@
0M
0>
0C
b1 [
b0 h
1=
b0 O
b0 R
b0 S
1-
#8400000
0-
#8450000
b10 [
1-
#8500000
0-
#8550000
b11 [
1-
#8600000
0-
#8650000
b100 [
1-
#8700000
0-
#8750000
b1000 8
b111110 3
1B
1'
b0 [
1-
#8800000
0-
#8850000
0B
b1 [
1-
#8900000
0-
#8950000
b10 [
1-
#9000000
0-
#9050000
b11 [
1-
#9100000
0-
#9150000
b100 [
1-
#9200000
0-
#9250000
14
1@
1M
1C
0'
b0 [
1-
#9300000
0-
#9350000
0C
b1 [
0K
0@
0L
0M
1I
b1000 d
1-
#9400000
0-
#9450000
b10 [
1-
#9500000
0-
#9550000
b11 [
1-
#9600000
0-
#9650000
b100 [
1-
#9700000
0-
#9750000
b1001 8
1B
1'
b0 [
1-
#9800000
0-
#9850000
0B
b1 [
1-
#9900000
0-
#9950000
b10 [
1-
#10000000
0-
#10050000
b11 [
1-
