calculadora/rtl/cores/Divisor/Corregir_Divisor.v
module Corregir_Signos #(
    parameter width = 31
)(
    input  signed [width:0] Residuo_NS,
    input  signed [width:0] Resultado_NS,
    input                   result_sign,
    input                   residue_sign,
    
    output signed [width:0] Residuo,
    output signed [width:0] Resultado
);
 
assign Resultado = result_sign  ? (~Resultado_NS + 1) : Resultado_NS;
assign Residuo   = residue_sign ? (~Residuo_NS   + 1) : Residuo_NS;
 
endmodule

calculadora/rtl/cores/Divisor/Sumador_Divisor.v
module Sumador_Divisor#(
    parameter width = 31 
)(
    input signed [width:0]  A, // el signed le dice a verilog que es un numero en complemento a dos, toma el MSB como bit de signo.
    input signed [width:0]  DR,  

    output signed [width:0] OUT,
    output MSB

);

// Resta en complemento a dos: in1 - in2
    assign OUT = A - DR;

// Bit de signo (MSB)
    assign MSB = OUT[width];

endmodule

calculadora/rtl/cores/Divisor/RegistroA_Divisor.v
module Registro_A #(
    parameter width = 31
)(
    input                   clk,
    input                   INIT,
    input                   LD,
    input                   SH,
    input        [width:0]  SUM_C2,
    input                   MSB_DV,

    output reg   [width:0]  Residuo_NS
);
 
always @(posedge clk) begin

    if (INIT)
        Residuo_NS <= 0;
   
    else if (LD)
        Residuo_NS <= SUM_C2;
   
    else if (SH)
        Residuo_NS <= {Residuo_NS[width-1:0], MSB_DV};
end

endmodule

calculadora/rtl/cores/Divisor/RegistroDV_Divisor.v
module Registro_DV #(
    parameter width = 31
)(
    input                   clk,
    input                   INIT,
    input                   SH,
    input                   DV0,
    input        [width:0]  Dividendo,
    output reg              MSB_DV,
    output reg   [width:0]  Resultado_NS
);

always @(posedge clk) begin
    if (INIT) begin
        Resultado_NS <= Dividendo;
        MSB_DV       <= Dividendo[width];
    end
    else if (SH) begin
        Resultado_NS <= {Resultado_NS[width-1:0], 1'b0};
        MSB_DV       <= Resultado_NS[width-1];
    end
    else if (DV0) begin
        Resultado_NS[0] <= 1'b1;
    end
end

endmodule

calculadora/rtl/cores/Divisor/Contador_Divisor.v
module Contador_Divisor(
    input   clk,    
    input   INIT,  
    input   DEC,
  
    output  reg [5:0] out,
    output  Z 
);
    always @(posedge clk) begin 

        if(INIT)
            out <= 6'd32;
        else if(DEC)
            out <= out - 1;
    end
    
    assign Z = (out == 0) ? 1 : 0; 

endmodule

calculadora/rtl/cores/Divisor/Control_Divisor.v
module Control_Divisor(

input clk,
input init,
input Z,
input MSB,
input corregir,
output reg LD,
output reg SH,
output reg DEC,
output reg DV0,
output reg DONE
);

// DEFINICIÓN DE ESTADOS
parameter S_START   = 3'b000;
parameter S_SHIFT   = 3'b001;
parameter S_CHECK   = 3'b010;
parameter S_ONE     = 3'b011;
parameter S_CORRECT = 3'b100;
parameter S_END     = 3'b101;

reg [2:0] NEXT_STATE;
reg [5:0] COUNT;

// MAQUINA DE ESTADOS
always @(posedge clk) begin
    case (NEXT_STATE)

        S_START: begin
            if (init) NEXT_STATE = S_SHIFT;
            else      NEXT_STATE = S_START;
        end

        S_SHIFT: begin
            NEXT_STATE = S_CHECK;
        end

        S_CHECK: begin
            if      (Z & corregir)  NEXT_STATE = S_CORRECT;
            else if (Z)             NEXT_STATE = S_END;
            else if (MSB)           NEXT_STATE = S_SHIFT;
            else                    NEXT_STATE = S_ONE;
        end

        S_ONE: begin
            NEXT_STATE = S_SHIFT;
        end

        S_CORRECT: begin
            NEXT_STATE = S_END;
        end

        S_END: begin
            COUNT      = COUNT + 1;
            NEXT_STATE = (COUNT > 30) ? S_START : S_END;
        end

        default: NEXT_STATE = S_START;

    endcase
end

// LOGICA DE SALIDAS
always @(*) begin
    case (NEXT_STATE)

        S_START: begin
            LD   = 0;
            SH   = 0;
            DEC  = 0;
            DV0  = 0;
            DONE = 0;
        end

        S_SHIFT: begin
            LD   = 0;
            SH   = 1;
            DEC  = 1;
            DV0  = 0;
            DONE = 0;
        end

        S_CHECK: begin
            LD   = 0;
            SH   = 0;
            DEC  = 0;
            DV0  = 0;
            DONE = 0;
        end

        S_ONE: begin
            LD   = 1;
            SH   = 0;
            DEC  = 0;
            DV0  = 1;
            DONE = 0;
        end

        S_CORRECT: begin
            LD   = 0;
            SH   = 0;
            DEC  = 0;
            DV0  = 0;
            DONE = 0;
        end

        S_END: begin
            LD   = 0;
            SH   = 0;
            DEC  = 0;
            DV0  = 0;
            DONE = 1;
        end

        default: begin
            LD   = 0;
            SH   = 0;
            DEC  = 0;
            DV0  = 0;
            DONE = 0;
        end

    endcase
end

endmodule

calculadora/rtl/cores/Divisor/Top_Divisor.v
module Divisor_Top #(
    parameter width = 31
)(
    input                    clk,
    input                    init,
    input signed  [width:0]  Dividendo,
    input signed  [width:0]  DR,

    output signed [width:0]  Residuo,
    output signed [width:0]  Resultado,
    output                   DONE
);

wire LD; 
wire SH;
wire DEC;
wire DV0;

wire              Z;
wire              MSB_DV;
wire              MSB;
wire [width:0]    SUM_C2_out;
wire [width:0]    Residuo_NS;
wire [width:0]    Resultado_NS;

wire result_sign  = Dividendo[width] ^ DR[width]; // Determina el signo del resultado de la division.
wire residue_sign = Dividendo[width]; // Se guarda el bit de signo del dividendo.

// Señal usada para indicar si luego debe corregirse el signo del cociente o del residuo.
wire corregir = result_sign | residue_sign;

// Obtiene el valor absoluto del dividendo.
wire [width:0] Dividendo_abs = Dividendo[width] ? (~Dividendo + 1) : Dividendo;

// Obtiene el valor absoluto del divisor.
wire [width:0] DR_abs        = DR[width]        ? (~DR + 1)        : DR;

Control_Divisor control (

    .clk      (clk),
    .init     (init),
    .Z        (Z),
    .MSB      (MSB),
    .corregir (corregir),
    .LD       (LD),
    .SH       (SH),
    .DEC      (DEC),
    .DV0      (DV0),
    .DONE     (DONE)

);

Contador_Divisor contador (

    .clk (clk),
    .INIT(init),
    .DEC (DEC),
    .out (),
    .Z   (Z)

);

Registro_DV #(.width(width)) reg_DV (

    .Dividendo (Dividendo_abs),  
    .clk         (clk),
    .INIT        (init),   
    .SH          (SH),
    .DV0         (DV0),
    .MSB_DV      (MSB_DV),
    .Resultado_NS(Resultado_NS)

);
Registro_A #(.width(width)) reg_A (

    .clk       (clk),
    .INIT      (init),
    .LD        (LD),
    .SH        (SH),
    .SUM_C2    (SUM_C2_out),
    .MSB_DV    (MSB_DV),
    .Residuo_NS(Residuo_NS)

);

Sumador_Divisor #(.width(width)) sumador (

    .DR (DR_abs),               
    .A   (Residuo_NS),
    .OUT (SUM_C2_out),
    .MSB (MSB)

);

Corregir_Signos #(.width(width)) corrector (

    .Residuo_NS  (Residuo_NS),
    .Resultado_NS(Resultado_NS),
    .result_sign (result_sign),
    .residue_sign(residue_sign),
    .Residuo     (Residuo),
    .Resultado   (Resultado)

);

endmodule

calculadora/rtl/cores/Divisor/Periferico_Divisor.v
module Periferico_Divisor (

    input         clk,
    input         reset,

    input  [31:0] d_in,   // dato que llega del procesador
    input         cs,     // chip select
    input  [4:0]  addr,   // dirección desde el bus
    input         rd,     // señal de lectura
    input         wr,     // señal de escritura

    output reg [31:0] d_out

);


// REGISTROS Y WIRES INTERNOS

reg [5:0] s;

reg signed [31:0] Dividendo;
reg signed [31:0] DR;

reg init;

wire signed [31:0] Resultado;
wire signed [31:0] Residuo;

wire DONE;

// DECODIFICADOR DE DIRECCIONES

always @(*) begin

    if (cs) begin
    
        case (addr)
    
            5'h04: s = 6'b000001; // Dividendo
            5'h08: s = 6'b000010; // DR (Divisor)
            5'h0C: s = 6'b000100; // init
            5'h10: s = 6'b001000; // Resultado (cociente)
            5'h14: s = 6'b010000; // Residuo
            5'h18: s = 6'b100000; // DONE
            default: s = 6'b000000;
        endcase
    
    end else
        s = 6'b000000;
end

// ESCRITURA DE REGISTROS

always @(posedge clk) begin
    
    if (reset) begin
        Dividendo <= 32'd0;
        DR        <= 32'd0;
        init      <= 1'b0;
    
    end else begin

    init <= 1'b0;

    if (cs && wr)
        Dividendo <= s[0] ? d_in    : Dividendo;
        DR        <= s[1] ? d_in    : DR;
        init      <= s[2] ? d_in[0] : 1'b0;
    
    end
end


// LECTURA DE REGISTROS

always @(*) begin // revisar si esta bien que sea COMBINACIONAL
    
    if (reset)
        d_out <= 32'd0;
    
    else if (cs && rd) begin
    
        case (s)
    
            6'b001000: d_out <= Resultado;
            6'b010000: d_out <= Residuo;
            6'b100000: d_out <= {31'b0, DONE};
            default:   d_out <= 32'd0;
    
        endcase
    end
end

// INSTANCIA DEL TOP DEL DIVISOR

Divisor_Top #(.width(31)) u_Divisor_Top (
    .clk       (clk),
    .init      (init),
    .Dividendo (Dividendo),
    .DR        (DR),
    .Resultado (Resultado),
    .Residuo   (Residuo),
    .DONE      (DONE)
);

endmodule

calculadora/rtl/cores/Divisor/Testbench_Divisor.v

`timescale 1ns/1ps

module tb_Periferico_Divisor;

reg clk;
reg reset;

reg [31:0] d_in;
reg cs;
reg [4:0] addr;
reg rd;
reg wr;

wire [31:0] d_out;

//====================================================
// DUT
//====================================================

Periferico_Divisor DUT(

    .clk(clk),
    .reset(reset),

    .d_in(d_in),
    .cs(cs),
    .addr(addr),
    .rd(rd),
    .wr(wr),

    .d_out(d_out)

);

//====================================================
// CLOCK
//====================================================

initial begin
    clk = 0;
    forever #5 clk = ~clk;
end

//====================================================
// GTKWave
//====================================================

initial begin

    $dumpfile("periferico_divisor.vcd");
    $dumpvars(0, tb_Periferico_Divisor);

end

//====================================================
// WRITE
//====================================================

task write_reg;

    input [4:0] address;
    input [31:0] data;

    begin

        @(posedge clk);

        cs   <= 1'b1;
        wr   <= 1'b1;
        rd   <= 1'b0;

        addr <= address;
        d_in <= data;

        @(posedge clk);

        cs   <= 1'b0;
        wr   <= 1'b0;

        addr <= 5'd0;
        d_in <= 32'd0;

    end

endtask

//====================================================
// READ
//====================================================

task read_reg;

    input [4:0] address;

    begin

        @(posedge clk);

        cs   <= 1'b1;
        rd   <= 1'b1;
        wr   <= 1'b0;

        addr <= address;

        @(posedge clk);

        $display("--------------------------------");
        $display("ADDR  = %h", address);
        $display("D_OUT = %0d", d_out);
        $display("--------------------------------");

        cs   <= 1'b0;
        rd   <= 1'b0;

        addr <= 5'd0;

    end

endtask

//====================================================
// TEST
//====================================================

initial begin

    reset = 1'b1;

    cs   = 0;
    rd   = 0;
    wr   = 0;

    addr = 0;
    d_in = 0;

    #20;

    reset = 1'b0;

    //========================================
    // Dividendo = 100
    //========================================

    write_reg(5'h04, 32'd100);

    //========================================
    // Divisor = 7
    //========================================

    write_reg(5'h08, 32'd7);

    //========================================
    // INIT
    //========================================

    write_reg(5'h0C, 32'd1);

    //========================================
    // Esperar DONE
    //========================================

    wait(DUT.DONE == 1'b1);

    #20;

    //========================================
    // Leer resultado
    //========================================

    read_reg(5'h10);

    //========================================
    // Leer residuo
    //========================================

    read_reg(5'h14);

    //========================================
    // Leer DONE
    //========================================

    read_reg(5'h18);

    #100;

    $finish;

end

endmodule



/*
`timescale 1ns/1ps

module tb_Divisor_Top;

    // =========================================================
    // PARAMETROS
    // =========================================================
    parameter width = 31;

    // =========================================================
    // ENTRADAS
    // =========================================================
    reg clk;
    reg init;

    reg signed [width:0] Dividendo;
    reg signed [width:0] DR;

    // =========================================================
    // SALIDAS
    // =========================================================
    wire signed [width:0] Residuo;
    wire signed [width:0] Resultado;
    wire DONE;

    // =========================================================
    // INSTANCIA DEL DUT
    // =========================================================
    Divisor_Top #(width) DUT (
        .clk        (clk),
        .init       (init),
        .Dividendo  (Dividendo),
        .DR         (DR),
        .Residuo    (Residuo),
        .Resultado  (Resultado),
        .DONE       (DONE)
    );

    // =========================================================
    // CLOCK
    // =========================================================
    initial begin
        clk = 0;
        forever #5 clk = ~clk;
    end

    // =========================================================
    // VARIABLES DEBUG
    // =========================================================
    integer ciclo;

    // NOMBRE DEL ESTADO
    reg [63:0] estado_nombre;
    always @(*) begin
        case (DUT.control.NEXT_STATE)
            3'b000: estado_nombre = "START  ";
            3'b001: estado_nombre = "SHIFT  ";
            3'b010: estado_nombre = "CHECK  ";
            3'b011: estado_nombre = "ONE    ";
            3'b100: estado_nombre = "CORRECT";
            3'b101: estado_nombre = "END    ";
            default: estado_nombre = "UNKNOWN";
        endcase
    end

    // =========================================================
    // GENERAR VCD
    // =========================================================
    initial begin
        $dumpfile("divisor_debug.vcd");
        $dumpvars(0, tb_Divisor_Top);
    end

    // =========================================================
    // HEADER TABLA
    // =========================================================
    initial begin
        $display("");
        $display("========================================================================================================================================================================================");
        $display("Tiempo | Ciclo | Estado  |LD|SH|DC|DV0|Z|M|CNT| A (Residuo_NS)                   | DV (Resultado_NS)                | SUM_C2_out                      ");
        $display("========================================================================================================================================================================================");
    end

    // =========================================================
    // DEBUG CICLO A CICLO
    // =========================================================
    always @(posedge clk) begin
        ciclo = ciclo + 1;
        $display("%6t | %5d | %s | %b| %b| %b| %b |%b|%b| %2d | %032b (%0d) | %032b (%0d) | %032b (%0d)",
            $time,
            ciclo,
            estado_nombre,
            DUT.LD,
            DUT.SH,
            DUT.DEC,
            DUT.DV0,
            DUT.Z,
            DUT.MSB,
            DUT.contador.out,
            DUT.Residuo_NS,   $signed(DUT.Residuo_NS),
            DUT.Resultado_NS, $signed(DUT.Resultado_NS),
            DUT.SUM_C2_out,   $signed(DUT.SUM_C2_out)
        );
    end

    // =========================================================
    // ESTIMULOS — cambia aqui los valores a probar
    // =========================================================
    initial begin
        ciclo    = 0;
        init     = 0;

        // -----------------------------------------------------
        // CASO ACTIVO — descomenta el que quieras probar
        // -----------------------------------------------------

        // positivo / positivo
        //Dividendo =  32'd25;
        //DR        =  32'd3;

        // negativo / positivo
        // Dividendo = -32'd25;
        // DR        =  32'd3;

        // positivo / negativo
        // Dividendo =  32'd25;
        // DR        = -32'd3;

        // negativo / negativo
        // Dividendo = -32'd25;
        // DR        = -32'd3;

        #20;
        init = 1;
        #10;
        init = 0;

        #1000;

        $display("");
        $display("==========================================================");
        $display("TIMEOUT");
        $display("Resultado = %032b (%0d)", Resultado, $signed(Resultado));
        $display("Residuo   = %032b (%0d)", Residuo,   $signed(Residuo));
        $display("DONE      = %b", DONE);
        $display("==========================================================");
        $finish;
    end

    // =========================================================
    // FINALIZAR SI DONE
    // =========================================================
    always @(posedge clk) begin
        if (DONE) begin
            $display("");
            $display("==========================================================");
            $display("DIVISION TERMINADA - Tiempo: %0t", $time);
            $display("Dividendo = %0d", $signed(Dividendo));
            $display("DR        = %0d", $signed(DR));
            $display("Resultado = %032b (%0d)", Resultado, $signed(Resultado));
            $display("Residuo   = %032b (%0d)", Residuo,   $signed(Residuo));
            $display("==========================================================");
            #20;
            $finish;
        end
    end

endmodule*/

calculadora/rtl/cores/Divisor/periferico_divisor.vcd
$date
	Thu May 14 12:24:33 2026
$end
$version
	Icarus Verilog
$end
$timescale
	1ps
$end
$scope module tb_Periferico_Divisor $end
$var wire 32 ! d_out [31:0] $end
$var reg 5 " addr [4:0] $end
$var reg 1 # clk $end
$var reg 1 $ cs $end
$var reg 32 % d_in [31:0] $end
$var reg 1 & rd $end
$var reg 1 ' reset $end
$var reg 1 ( wr $end
$scope module DUT $end
$var wire 5 ) addr [4:0] $end
$var wire 1 # clk $end
$var wire 1 $ cs $end
$var wire 32 * d_in [31:0] $end
$var wire 1 & rd $end
$var wire 1 ' reset $end
$var wire 1 ( wr $end
$var wire 32 + Resultado [31:0] $end
$var wire 32 , Residuo [31:0] $end
$var wire 1 - DONE $end
$var reg 32 . DR [31:0] $end
$var reg 32 / Dividendo [31:0] $end
$var reg 32 0 d_out [31:0] $end
$var reg 1 1 init $end
$var reg 6 2 s [5:0] $end
$scope module u_Divisor_Top $end
$var wire 32 3 DR [31:0] $end
$var wire 32 4 Dividendo [31:0] $end
$var wire 1 # clk $end
$var wire 1 5 corregir $end
$var wire 1 1 init $end
$var wire 1 6 result_sign $end
$var wire 1 7 residue_sign $end
$var wire 1 8 Z $end
$var wire 32 9 SUM_C2_out [31:0] $end
$var wire 1 : SH $end
$var wire 32 ; Resultado_NS [31:0] $end
$var wire 32 < Resultado [31:0] $end
$var wire 32 = Residuo_NS [31:0] $end
$var wire 32 > Residuo [31:0] $end
$var wire 1 ? MSB_DV $end
$var wire 1 @ MSB $end
$var wire 1 A LD $end
$var wire 32 B Dividendo_abs [31:0] $end
$var wire 1 C DV0 $end
$var wire 32 D DR_abs [31:0] $end
$var wire 1 - DONE $end
$var wire 1 E DEC $end
$var parameter 32 F width $end
$scope module contador $end
$var wire 1 1 INIT $end
$var wire 1 # clk $end
$var wire 1 8 Z $end
$var wire 1 E DEC $end
$var reg 6 G out [5:0] $end
$upscope $end
$scope module control $end
$var wire 1 8 Z $end
$var wire 1 # clk $end
$var wire 1 5 corregir $end
$var wire 1 1 init $end
$var wire 1 @ MSB $end
$var parameter 3 H S_CHECK $end
$var parameter 3 I S_CORRECT $end
$var parameter 3 J S_END $end
$var parameter 3 K S_ONE $end
$var parameter 3 L S_SHIFT $end
$var parameter 3 M S_START $end
$var reg 6 N COUNT [5:0] $end
$var reg 1 E DEC $end
$var reg 1 - DONE $end
$var reg 1 C DV0 $end
$var reg 1 A LD $end
$var reg 3 O NEXT_STATE [2:0] $end
$var reg 1 : SH $end
$upscope $end
$scope module corrector $end
$var wire 1 7 residue_sign $end
$var wire 1 6 result_sign $end
$var wire 32 P Resultado_NS [31:0] $end
$var wire 32 Q Resultado [31:0] $end
$var wire 32 R Residuo_NS [31:0] $end
$var wire 32 S Residuo [31:0] $end
$var parameter 32 T width $end
$upscope $end
$scope module reg_A $end
$var wire 1 1 INIT $end
$var wire 1 A LD $end
$var wire 1 : SH $end
$var wire 1 # clk $end
$var wire 32 U SUM_C2 [31:0] $end
$var wire 1 ? MSB_DV $end
$var parameter 32 V width $end
$var reg 32 W Residuo_NS [31:0] $end
$upscope $end
$scope module reg_DV $end
$var wire 1 C DV0 $end
$var wire 32 X Dividendo [31:0] $end
$var wire 1 1 INIT $end
$var wire 1 : SH $end
$var wire 1 # clk $end
$var parameter 32 Y width $end
$var reg 1 ? MSB_DV $end
$var reg 32 Z Resultado_NS [31:0] $end
$upscope $end
$scope module sumador $end
$var wire 32 [ A [31:0] $end
$var wire 32 \ DR [31:0] $end
$var wire 32 ] OUT [31:0] $end
$var wire 1 @ MSB $end
$var parameter 32 ^ width $end
$upscope $end
$upscope $end
$upscope $end
$scope task read_reg $end
$var reg 5 _ address [4:0] $end
$upscope $end
$scope task write_reg $end
$var reg 5 ` address [4:0] $end
$var reg 32 a data [31:0] $end
$upscope $end
$upscope $end
$enddefinitions $end
$comment Show the parameter values. $end
$dumpall
b11111 ^
b11111 Y
b11111 V
b11111 T
b0 M
b1 L
b11 K
b101 J
b100 I
b10 H
b11111 F
$end
#0
$dumpvars
bx a
bx `
bx _
bx ]
bx \
bx [
bx Z
bx X
bx W
bx U
bx S
bx R
bx Q
bx P
bx O
bx N
bx G
xE
bx D
xC
bx B
xA
x@
x?
bx >
bx =
bx <
bx ;
x:
bx 9
x8
x7
x6
x5
bx 4
bx 3
b0 2
x1
b0 0
bx /
bx .
x-
bx ,
bx +
b0 *
b0 )
0(
1'
0&
b0 %
0$
0#
b0 "
b0 !
$end
#5000
05
b0 D
b0 \
06
b0 B
b0 X
07
01
b0 .
b0 3
b0 /
b0 4
0-
0C
0E
0:
0A
b0 O
1#
#10000
0#
#15000
1#
#20000
0#
b1100100 a
b100 `
0'
#25000
b1 2
b1100100 %
b1100100 *
b100 "
b100 )
1(
1$
1#
#30000
0#
#35000
b0 2
b1100100 B
b1100100 X
b0 %
b0 *
b0 "
b0 )
0(
0$
b1100100 /
b1100100 4
b111 a
b1000 `
1#
#40000
0#
#45000
b10 2
b111 %
b111 *
b1000 "
b1000 )
1(
1$
1#
#50000
0#
#55000
b0 2
b111 D
b111 \
b0 %
b0 *
b0 "
b0 )
0(
0$
b111 .
b111 3
b1 a
b1100 `
1#
#60000
0#
#65000
b100 2
b1 %
b1 *
b1100 "
b1100 )
1(
1$
1#
#70000
0#
#75000
b0 2
b0 %
b0 *
b0 "
b0 )
0(
0$
11
1#
#80000
0#
#85000
08
b1100100 +
b1100100 <
b1100100 Q
1@
b0 ,
b0 >
b0 S
b100000 G
0?
b1100100 ;
b1100100 P
b1100100 Z
b11111111111111111111111111111001 9
b11111111111111111111111111111001 U
b11111111111111111111111111111001 ]
b0 =
b0 R
b0 W
b0 [
01
1E
1:
b1 O
1#
#90000
0#
#95000
b11001000 +
b11001000 <
b11001000 Q
b11001000 ;
b11001000 P
b11001000 Z
b11111 G
0E
0:
b10 O
1#
#100000
0#
#105000
1E
1:
b1 O
1#
#110000
0#
#115000
b110010000 +
b110010000 <
b110010000 Q
b110010000 ;
b110010000 P
b110010000 Z
b11110 G
0E
0:
b10 O
1#
#120000
0#
#125000
1E
1:
b1 O
1#
#130000
0#
#135000
b1100100000 +
b1100100000 <
b1100100000 Q
b1100100000 ;
b1100100000 P
b1100100000 Z
b11101 G
0E
0:
b10 O
1#
#140000
0#
#145000
1E
1:
b1 O
1#
#150000
0#
#155000
b11001000000 +
b11001000000 <
b11001000000 Q
b11001000000 ;
b11001000000 P
b11001000000 Z
b11100 G
0E
0:
b10 O
1#
#160000
0#
#165000
1E
1:
b1 O
1#
#170000
0#
#175000
b110010000000 +
b110010000000 <
b110010000000 Q
b110010000000 ;
b110010000000 P
b110010000000 Z
b11011 G
0E
0:
b10 O
1#
#180000
0#
#185000
1E
1:
b1 O
1#
#190000
0#
#195000
b1100100000000 +
b1100100000000 <
b1100100000000 Q
b1100100000000 ;
b1100100000000 P
b1100100000000 Z
b11010 G
0E
0:
b10 O
1#
#200000
0#
#205000
1E
1:
b1 O
1#
#210000
0#
#215000
b11001000000000 +
b11001000000000 <
b11001000000000 Q
b11001000000000 ;
b11001000000000 P
b11001000000000 Z
b11001 G
0E
0:
b10 O
1#
#220000
0#
#225000
1E
1:
b1 O
1#
#230000
0#
#235000
b110010000000000 +
b110010000000000 <
b110010000000000 Q
b110010000000000 ;
b110010000000000 P
b110010000000000 Z
b11000 G
0E
0:
b10 O
1#
#240000
0#
#245000
1E
1:
b1 O
1#
#250000
0#
#255000
b1100100000000000 +
b1100100000000000 <
b1100100000000000 Q
b1100100000000000 ;
b1100100000000000 P
b1100100000000000 Z
b10111 G
0E
0:
b10 O
1#
#260000
0#
#265000
1E
1:
b1 O
1#
#270000
0#
#275000
b11001000000000000 +
b11001000000000000 <
b11001000000000000 Q
b11001000000000000 ;
b11001000000000000 P
b11001000000000000 Z
b10110 G
0E
0:
b10 O
1#
#280000
0#
#285000
1E
1:
b1 O
1#
#290000
0#
#295000
b110010000000000000 +
b110010000000000000 <
b110010000000000000 Q
b110010000000000000 ;
b110010000000000000 P
b110010000000000000 Z
b10101 G
0E
0:
b10 O
1#
#300000
0#
#305000
1E
1:
b1 O
1#
#310000
0#
#315000
b1100100000000000000 +
b1100100000000000000 <
b1100100000000000000 Q
b1100100000000000000 ;
b1100100000000000000 P
b1100100000000000000 Z
b10100 G
0E
0:
b10 O
1#
#320000
0#
#325000
1E
1:
b1 O
1#
#330000
0#
#335000
b11001000000000000000 +
b11001000000000000000 <
b11001000000000000000 Q
b11001000000000000000 ;
b11001000000000000000 P
b11001000000000000000 Z
b10011 G
0E
0:
b10 O
1#
#340000
0#
#345000
1E
1:
b1 O
1#
#350000
0#
#355000
b110010000000000000000 +
b110010000000000000000 <
b110010000000000000000 Q
b110010000000000000000 ;
b110010000000000000000 P
b110010000000000000000 Z
b10010 G
0E
0:
b10 O
1#
#360000
0#
#365000
1E
1:
b1 O
1#
#370000
0#
#375000
b1100100000000000000000 +
b1100100000000000000000 <
b1100100000000000000000 Q
b1100100000000000000000 ;
b1100100000000000000000 P
b1100100000000000000000 Z
b10001 G
0E
0:
b10 O
1#
#380000
0#
#385000
1E
1:
b1 O
1#
#390000
0#
#395000
b11001000000000000000000 +
b11001000000000000000000 <
b11001000000000000000000 Q
b11001000000000000000000 ;
b11001000000000000000000 P
b11001000000000000000000 Z
b10000 G
0E
0:
b10 O
1#
#400000
0#
#405000
1E
1:
b1 O
1#
#410000
0#
#415000
b110010000000000000000000 +
b110010000000000000000000 <
b110010000000000000000000 Q
b110010000000000000000000 ;
b110010000000000000000000 P
b110010000000000000000000 Z
b1111 G
0E
0:
b10 O
1#
#420000
0#
#425000
1E
1:
b1 O
1#
#430000
0#
#435000
b1100100000000000000000000 +
b1100100000000000000000000 <
b1100100000000000000000000 Q
b1100100000000000000000000 ;
b1100100000000000000000000 P
b1100100000000000000000000 Z
b1110 G
0E
0:
b10 O
1#
#440000
0#
#445000
1E
1:
b1 O
1#
#450000
0#
#455000
b11001000000000000000000000 +
b11001000000000000000000000 <
b11001000000000000000000000 Q
b11001000000000000000000000 ;
b11001000000000000000000000 P
b11001000000000000000000000 Z
b1101 G
0E
0:
b10 O
1#
#460000
0#
#465000
1E
1:
b1 O
1#
#470000
0#
#475000
b110010000000000000000000000 +
b110010000000000000000000000 <
b110010000000000000000000000 Q
b110010000000000000000000000 ;
b110010000000000000000000000 P
b110010000000000000000000000 Z
b1100 G
0E
0:
b10 O
1#
#480000
0#
#485000
1E
1:
b1 O
1#
#490000
0#
#495000
b1100100000000000000000000000 +
b1100100000000000000000000000 <
b1100100000000000000000000000 Q
b1100100000000000000000000000 ;
b1100100000000000000000000000 P
b1100100000000000000000000000 Z
b1011 G
0E
0:
b10 O
1#
#500000
0#
#505000
1E
1:
b1 O
1#
#510000
0#
#515000
b11001000000000000000000000000 +
b11001000000000000000000000000 <
b11001000000000000000000000000 Q
b11001000000000000000000000000 ;
b11001000000000000000000000000 P
b11001000000000000000000000000 Z
b1010 G
0E
0:
b10 O
1#
#520000
0#
#525000
1E
1:
b1 O
1#
#530000
0#
#535000
b110010000000000000000000000000 +
b110010000000000000000000000000 <
b110010000000000000000000000000 Q
b110010000000000000000000000000 ;
b110010000000000000000000000000 P
b110010000000000000000000000000 Z
b1001 G
0E
0:
b10 O
1#
#540000
0#
#545000
1E
1:
b1 O
1#
#550000
0#
#555000
b1100100000000000000000000000000 +
b1100100000000000000000000000000 <
b1100100000000000000000000000000 Q
b1100100000000000000000000000000 ;
b1100100000000000000000000000000 P
b1100100000000000000000000000000 Z
b1000 G
0E
0:
b10 O
1#
#560000
0#
#565000
1E
1:
b1 O
1#
#570000
0#
#575000
b11001000000000000000000000000000 +
b11001000000000000000000000000000 <
b11001000000000000000000000000000 Q
1?
b11001000000000000000000000000000 ;
b11001000000000000000000000000000 P
b11001000000000000000000000000000 Z
b111 G
0E
0:
b10 O
1#
#580000
0#
#585000
1E
1:
b1 O
1#
#590000
0#
#595000
b1 ,
b1 >
b1 S
b10010000000000000000000000000000 +
b10010000000000000000000000000000 <
b10010000000000000000000000000000 Q
b11111111111111111111111111111010 9
b11111111111111111111111111111010 U
b11111111111111111111111111111010 ]
b1 =
b1 R
b1 W
b1 [
b10010000000000000000000000000000 ;
b10010000000000000000000000000000 P
b10010000000000000000000000000000 Z
b110 G
0E
0:
b10 O
1#
#600000
0#
#605000
1E
1:
b1 O
1#
#610000
0#
#615000
b11 ,
b11 >
b11 S
b100000000000000000000000000000 +
b100000000000000000000000000000 <
b100000000000000000000000000000 Q
b11111111111111111111111111111100 9
b11111111111111111111111111111100 U
b11111111111111111111111111111100 ]
b11 =
b11 R
b11 W
b11 [
0?
b100000000000000000000000000000 ;
b100000000000000000000000000000 P
b100000000000000000000000000000 Z
b101 G
0E
0:
b10 O
1#
#620000
0#
#625000
1E
1:
b1 O
1#
#630000
0#
#635000
b110 ,
b110 >
b110 S
b1000000000000000000000000000000 +
b1000000000000000000000000000000 <
b1000000000000000000000000000000 Q
b11111111111111111111111111111111 9
b11111111111111111111111111111111 U
b11111111111111111111111111111111 ]
b110 =
b110 R
b110 W
b110 [
b1000000000000000000000000000000 ;
b1000000000000000000000000000000 P
b1000000000000000000000000000000 Z
b100 G
0E
0:
b10 O
1#
#640000
0#
#645000
1E
1:
b1 O
1#
#650000
0#
#655000
0@
b1100 ,
b1100 >
b1100 S
b10000000000000000000000000000000 +
b10000000000000000000000000000000 <
b10000000000000000000000000000000 Q
b101 9
b101 U
b101 ]
b1100 =
b1100 R
b1100 W
b1100 [
1?
b10000000000000000000000000000000 ;
b10000000000000000000000000000000 P
b10000000000000000000000000000000 Z
b11 G
0E
0:
b10 O
1#
#660000
0#
#665000
1C
1A
b11 O
1#
#670000
0#
#675000
1@
b101 ,
b101 >
b101 S
b10000000000000000000000000000001 +
b10000000000000000000000000000001 <
b10000000000000000000000000000001 Q
b11111111111111111111111111111110 9
b11111111111111111111111111111110 U
b11111111111111111111111111111110 ]
b101 =
b101 R
b101 W
b101 [
b10000000000000000000000000000001 ;
b10000000000000000000000000000001 P
b10000000000000000000000000000001 Z
0C
1E
1:
0A
b1 O
1#
#680000
0#
#685000
b10 +
b10 <
b10 Q
0@
b1011 ,
b1011 >
b1011 S
b10 G
0?
b10 ;
b10 P
b10 Z
b100 9
b100 U
b100 ]
b1011 =
b1011 R
b1011 W
b1011 [
0E
0:
b10 O
1#
#690000
0#
#695000
1C
1A
b11 O
1#
#700000
0#
#705000
b11 +
b11 <
b11 Q
1@
b100 ,
b100 >
b100 S
b11 ;
b11 P
b11 Z
b11111111111111111111111111111101 9
b11111111111111111111111111111101 U
b11111111111111111111111111111101 ]
b100 =
b100 R
b100 W
b100 [
0C
1E
1:
0A
b1 O
1#
#710000
0#
#715000
0@
b1000 ,
b1000 >
b1000 S
b110 +
b110 <
b110 Q
b1 9
b1 U
b1 ]
b1000 =
b1000 R
b1000 W
b1000 [
b110 ;
b110 P
b110 Z
b1 G
0E
0:
b10 O
1#
#720000
0#
#725000
1C
1A
b11 O
1#
#730000
0#
