proyecto principal/controlador ads1115/I2C/CONTROL.v
module CONTROL_I2C (
    input wire clk,
    input wire rst,
    input wire start,
    input wire rw,
    input wire scl_rise,
    input wire scl_fall,
    input wire z_bits,
    input wire z_bytes,
    input wire sda_in,
    input wire [7:0] byte_value,

    output reg scl_enable,
    output reg sda_mux_sel,
    output reg sda_force_low,
    output reg load_shift,
    output reg shift_tx,
    output reg shift_rx,
    output reg store_rx,
    output reg load_bit_counter,
    output reg dec_bit_counter,
    output reg load_byte_counter,
    output reg dec_byte_counter,
    output reg busy,
    output reg done,
    output reg ack_error,
    output reg byte_done
);

    // DEFINICIÓN DE ESTADOS
    parameter S_IDLE      = 10'b0000000001;
    parameter S_START     = 10'b0000000010;
    parameter S_TX_DATA   = 10'b0000000100;
    parameter S_RX_ACK    = 10'b0000001000;
    parameter S_RX_DATA   = 10'b0000010000;
    parameter S_TX_ACK    = 10'b0000100000;
    parameter S_BYTE_DONE = 10'b0001000000;
    parameter S_STOP      = 10'b0010000000;
    parameter S_STOP_WAIT = 10'b0100000000;
    parameter S_DONE      = 10'b1000000000;

    reg [9:0] NEXT_STATE;
    reg [7:0] delay_cnt;

    always @(posedge clk or posedge rst) begin
        if (rst) begin
            NEXT_STATE <= S_IDLE;
            ack_error  <= 0;
            delay_cnt  <= 0;
        end else begin

            // Administrador del contador de retardos I2C
            if (NEXT_STATE == S_STOP_WAIT || NEXT_STATE == S_DONE)
                delay_cnt <= delay_cnt + 1'b1;
            else
                delay_cnt <= 0;

            case (NEXT_STATE)
                S_IDLE: begin
                    ack_error <= 0;
                    if (start) NEXT_STATE <= S_START;
                    else       NEXT_STATE <= S_IDLE;
                end
                S_START: begin
                    if (scl_fall) NEXT_STATE <= S_TX_DATA;
                    else          NEXT_STATE <= S_START;
                end
                S_TX_DATA: begin
                    if (scl_fall && z_bits) NEXT_STATE <= S_RX_ACK;
                    else                    NEXT_STATE <= S_TX_DATA;
                end
                S_RX_ACK: begin
                    if (scl_rise && sda_in) ack_error <= 1;
                    if (scl_fall)           NEXT_STATE <= S_BYTE_DONE;
                    else                    NEXT_STATE <= S_RX_ACK;
                end
                S_RX_DATA: begin
                    if (scl_fall && z_bits) NEXT_STATE <= S_TX_ACK;
                    else                    NEXT_STATE <= S_RX_DATA;
                end
                S_TX_ACK: begin
                    if (scl_fall) NEXT_STATE <= S_BYTE_DONE;
                    else          NEXT_STATE <= S_TX_ACK;
                end
                S_BYTE_DONE: begin
                    if (ack_error)    NEXT_STATE <= S_STOP;
                    else if (z_bytes) NEXT_STATE <= S_STOP;
                    else begin
                        if (rw) NEXT_STATE <= S_RX_DATA;
                        else    NEXT_STATE <= S_TX_DATA;
                    end
                end
                S_STOP: begin
                    if (scl_rise) NEXT_STATE <= S_STOP_WAIT;
                    else          NEXT_STATE <= S_STOP;
                end
                S_STOP_WAIT: begin
                    // Espera 5 microsegundos (125 ciclos @ 25MHz) antes de liberar SDA
                    if (delay_cnt >= 8'd125) NEXT_STATE <= S_DONE;
                    else                     NEXT_STATE <= S_STOP_WAIT;
                end
                S_DONE: begin
                    // Espera 5 microsegundos extra antes de finalizar
                    if (delay_cnt >= 8'd250) NEXT_STATE <= S_IDLE;
                    else                     NEXT_STATE <= S_DONE;
                end
                default: NEXT_STATE <= S_IDLE;
            endcase
        end
    end

    // LOGICA DE SALIDAS 
    always @(*) begin
        case (NEXT_STATE)
            S_IDLE: begin
                scl_enable    = 0; load_bit_counter  = 0;
                sda_mux_sel   = 1; dec_bit_counter   = 0;
                sda_force_low = 0; load_byte_counter = 0;
                load_shift    = 0; dec_byte_counter  = 0;
                shift_tx      = 0; busy              = 0;
                shift_rx      = 0; done              = 0;
                store_rx      = 0; byte_done         = 0;
            end
            S_START: begin
                scl_enable    = 1; load_bit_counter  = 1;
                sda_mux_sel   = 1; dec_bit_counter   = 0;
                sda_force_low = 1; load_byte_counter = 1;
                load_shift    = 1; dec_byte_counter  = 0;
                shift_tx      = 0; busy              = 1;
                shift_rx      = 0; done              = 0;
                store_rx      = 0; byte_done         = 0;
            end
            S_TX_DATA: begin
                scl_enable    = 1;        load_bit_counter  = 0;
                sda_mux_sel   = 0;        dec_bit_counter   = scl_fall;
                sda_force_low = 0;        load_byte_counter = 0;
                load_shift    = 0;        dec_byte_counter  = 0;
                shift_tx      = scl_fall; busy              = 1;
                shift_rx      = 0;        done              = 0;
                store_rx      = 0;        byte_done         = 0;
            end
            S_RX_ACK: begin
                scl_enable    = 1; load_bit_counter  = 0;
                sda_mux_sel   = 1; dec_bit_counter   = 0;
                sda_force_low = 0; load_byte_counter = 0;
                load_shift    = 0; dec_byte_counter  = scl_fall;
                shift_tx      = 0; busy              = 1;
                shift_rx      = 0; done              = 0;
                store_rx      = 0; byte_done         = 0;
            end
            S_RX_DATA: begin
                scl_enable    = 1;        load_bit_counter  = 0;
                sda_mux_sel   = 1;        dec_bit_counter   = scl_fall;
                sda_force_low = 0;        load_byte_counter = 0;
                load_shift    = 0;        dec_byte_counter  = 0;
                shift_tx      = 0;        busy              = 1;
                shift_rx      = scl_rise; done              = 0;
                store_rx      = 0;        byte_done         = 0;
            end
            S_TX_ACK: begin
                scl_enable    = 1;                                   load_bit_counter  = 0;
                sda_mux_sel   = 1;                                   dec_bit_counter   = 0;
                sda_force_low = (byte_value == 8'd1) ? 1'b0 : 1'b1;  load_byte_counter = 0;
                load_shift    = 0;                                   dec_byte_counter  = scl_fall;
                shift_tx      = 0;                                   busy              = 1;
                shift_rx      = 0;                                   done              = 0;
                store_rx      = scl_rise;                            byte_done         = 0;
            end
            S_BYTE_DONE: begin
                scl_enable    = 1;                 load_bit_counter  = 1;
                sda_mux_sel   = 1;                 dec_bit_counter   = 0;
                sda_force_low = 1;                 load_byte_counter = 0;
                load_shift    = (~z_bytes && ~rw); dec_byte_counter  = 0;
                shift_tx      = 0;                 busy              = 1;
                shift_rx      = 0;                 done              = 0;
                store_rx      = 0;                 byte_done         = 1;
            end
            S_STOP: begin
                scl_enable    = 1; load_bit_counter  = 0;
                sda_mux_sel   = 1; dec_bit_counter   = 0;
                sda_force_low = 1; load_byte_counter = 0;
                load_shift    = 0; dec_byte_counter  = 0;
                shift_tx      = 0; busy              = 1;
                shift_rx      = 0; done              = 0;
                store_rx      = 0; byte_done         = 0;
            end
            S_STOP_WAIT: begin
                scl_enable    = 1; load_bit_counter  = 0;
                sda_mux_sel   = 1; dec_bit_counter   = 0;
                sda_force_low = 1; load_byte_counter = 0;
                load_shift    = 0; dec_byte_counter  = 0;
                shift_tx      = 0; busy              = 1;
                shift_rx      = 0; done              = 0;
                store_rx      = 0; byte_done         = 0;
            end
            S_DONE: begin
                scl_enable    = 0; load_bit_counter  = 0;
                sda_mux_sel   = 1; dec_bit_counter   = 0;
                sda_force_low = 0; load_byte_counter = 0; 
                load_shift    = 0; dec_byte_counter  = 0;
                shift_tx      = 0; busy              = 1; 
                shift_rx      = 0; done              = (delay_cnt >= 8'd250);
                store_rx      = 0; byte_done         = 0;
            end
            default: begin
                scl_enable    = 0; load_bit_counter  = 0;
                sda_mux_sel   = 0; dec_bit_counter   = 0;
                sda_force_low = 0; load_byte_counter = 0;
                load_shift    = 0; dec_byte_counter  = 0;
                shift_tx      = 0; busy              = 0;
                shift_rx      = 0; done              = 0;
                store_rx      = 0; byte_done         = 0;
            end
        endcase
    end
endmodule

proyecto principal/controlador ads1115/I2C/CONTADOR_BYTES.v
module CONTADOR_BYTES(
    input  wire clk,
    input  wire rst,
    input  wire load,
    input  wire dec,
    input  wire [7:0] num_bytes,

    output wire z_bytes,
    output wire [7:0] value
);
    reg [7:0] count;

    always @(posedge clk or posedge rst) begin
        if (rst)
            count <= 8'd0;

        else if (load)
            count <= num_bytes;

        else if (dec && (count != 8'd0))
            count <= count - 8'd1;
    end

    assign z_bytes = (count == 8'd0);
    assign value   = count;
    
endmodule

proyecto principal/I2C/CONTADOR_BITS.v
module CONTADOR_BITS(
    input  wire clk,
    input  wire rst,
    input  wire load,
    input  wire dec,

    output wire z_bits,
    output wire [2:0] value
);

    reg [2:0] count;

    always @(posedge clk or posedge rst) begin

        if (rst)
            count <= 3'd0;

        else if (load)
            count <= 3'd7;

        else if (dec && (count != 3'd0))
            count <= count - 3'd1;
    end

    assign z_bits = (count == 3'd0);
    assign value  = count;

endmodule

proyecto principal/controlador ads1115/I2C/SHIFT_REG.v
module SHIFT_REGISTER(
    input  wire       clk,
    input  wire       rst,
    input  wire       load,
    input  wire       shift_tx,
    input  wire       shift_rx,
    input  wire       store_rx,
    input  wire [7:0] tx_byte,
    input  wire       sda_in,

    output wire       tx_bit,
    output wire [7:0] rx_data
);

    reg [7:0] shift_reg;
    reg [7:0] rx_reg;

    // logica del registro de desplazamiento (shift_reg)
    always @(posedge clk or posedge rst) begin
        if (rst) begin
            shift_reg <= 8'd0;

        end else if (load) begin
            shift_reg <= tx_byte;

        end else if (shift_tx) begin
            shift_reg <= {shift_reg[6:0], 1'b0};     

        end else if (shift_rx) begin
            shift_reg <= {shift_reg[6:0], sda_in};            
        end
    end

    always @(posedge clk or posedge rst) begin
        if (rst) begin
            rx_reg <= 8'd0;

        end else if (store_rx) begin
            rx_reg <= shift_reg;
        end
    end

    assign tx_bit  = shift_reg[7];
    assign rx_data = rx_reg;

endmodule

proyecto principal/I2C/I2C_CLOCK_GENERATOR.v
module I2C_CLOCK_GENERATOR #(
    parameter CLK_FREQ_HZ = 25_000_000,
    parameter I2C_FREQ_HZ = 100_000
)(
    input  wire clk,
    input  wire rst,
    input  wire enable,

    output reg  scl,
    output reg  scl_rise,
    output reg  scl_fall
);

    // Cálculo del número de ciclos de reloj por cada semiciclo I2C
    localparam HALF_PERIOD = CLK_FREQ_HZ / (2 * I2C_FREQ_HZ);    
    // Calcula automáticamente los bits necesarios para el contador
    localparam COUNTER_WIDTH = $clog2(HALF_PERIOD);

    reg [COUNTER_WIDTH-1:0] counter;

    always @(posedge clk or posedge rst) begin
        if (rst) begin
            counter  <= 0;
            scl      <= 1'b1; 
            scl_rise <= 1'b0;
            scl_fall <= 1'b0;
            
        end else if (!enable) begin
            counter  <= 0;
            scl      <= 1'b1; 
            scl_rise <= 1'b0;
            scl_fall <= 1'b0;
            
        end else if (counter == HALF_PERIOD - 1) begin
            counter  <= 0;
            scl      <= ~scl;     
            scl_rise <= ~scl;     
            scl_fall <= scl;      
            
        end else begin
            counter  <= counter + 1'b1;
            scl_rise <= 1'b0;
            scl_fall <= 1'b0;
        end
    end

endmodule

proyecto principal/controlador_ADS1115/I2C/Top_I2C.v
module TOP_I2C #(
    parameter CLK_FREQ_HZ = 25_000_000,
    parameter I2C_FREQ_HZ = 100_000
)(
    input  wire clk,
    input  wire rst,
    input  wire start,
    input  wire rw,
    input  wire [7:0] tx_byte,
    input  wire [7:0] num_bytes,

    output wire [7:0] rx_data,
    output wire busy,
    output wire done,
    output wire ack_error,
    output wire byte_done,
    
    inout wire SDA,
    inout wire SCL
);

    // Señales internas de reloj I2C 
    wire scl_enable;
    wire scl_rise;
    wire scl_fall;
    wire scl_internal;

    // Señales de control de SDA
    wire sda_mux_sel;
    wire sda_force_low;
    wire sda_pull_low;
    wire sda_in;
    wire tx_bit;

    // Señales de control del registro de desplazamiento
    wire load_shift;
    wire shift_tx;
    wire shift_rx;
    wire store_rx;

    // Señales de control de los contadores
    wire load_bit_counter;
    wire dec_bit_counter;
    wire z_bits;
    wire [2:0] bit_value;

    wire load_byte_counter;
    wire dec_byte_counter;
    wire z_bytes;
    wire [7:0] byte_value;

    // bloque para sincronizar la señal de entrada de SDA con el relog de la FPGA
    reg sda_meta, sda_sync;
    always @(posedge clk or posedge rst) begin
        if (rst) begin
            sda_meta <= 1'b1;
            sda_sync <= 1'b1;
        end else begin
            sda_meta <= SDA;
            sda_sync <= sda_meta;
        end
    end
    assign sda_in = sda_sync;

   // I2C utiliza salidas Open-Drain: drive_low = 1 -> fuerza un '0' drive_low = 0 -> alta impedancia
    assign SDA = sda_pull_low ? 1'b0 : 1'bz;
    assign sda_pull_low = (sda_mux_sel) ? sda_force_low : ~tx_bit;
    assign SCL = (scl_internal) ? 1'bz : 1'b0;

    I2C_CLOCK_GENERATOR #(
        .CLK_FREQ_HZ(CLK_FREQ_HZ),
        .I2C_FREQ_HZ(I2C_FREQ_HZ)
    )
    CLOCK_GEN(
        .clk      (clk),
        .rst      (rst),
        .enable   (scl_enable),
        .scl      (scl_internal),
        .scl_rise (scl_rise),
        .scl_fall (scl_fall)
    );
    SHIFT_REGISTER SHIFT(
        .clk      (clk),
        .rst      (rst),
        .load     (load_shift),
        .shift_tx (shift_tx),
        .shift_rx (shift_rx),
        .store_rx (store_rx),
        .tx_byte  (tx_byte),
        .sda_in   (sda_in),
        .tx_bit   (tx_bit),
        .rx_data  (rx_data)
    );
    CONTADOR_BITS BIT_COUNTER(
        .clk    (clk),
        .rst    (rst),
        .load   (load_bit_counter),
        .dec    (dec_bit_counter),
        .z_bits (z_bits),
        .value  (bit_value)
    );
    CONTADOR_BYTES BYTE_COUNTER(
        .clk       (clk),
        .rst       (rst),
        .load      (load_byte_counter),
        .dec       (dec_byte_counter),
        .num_bytes (num_bytes),
        .z_bytes   (z_bytes),
        .value     (byte_value)
    );
    CONTROL_I2C CONTROL (
        .clk      (clk),
        .rst      (rst),
        .start    (start),
        .rw       (rw),
        .scl_rise (scl_rise),
        .scl_fall (scl_fall),
        .z_bits   (z_bits),
        .z_bytes  (z_bytes),
        .sda_in   (sda_in),
        .byte_value(byte_value),
        .scl_enable    (scl_enable),
        .sda_mux_sel   (sda_mux_sel),
        .sda_force_low (sda_force_low),
        .load_shift    (load_shift),
        .shift_tx      (shift_tx),
        .shift_rx      (shift_rx),
        .store_rx      (store_rx),
        .load_bit_counter  (load_bit_counter),
        .dec_bit_counter   (dec_bit_counter),
        .load_byte_counter (load_byte_counter),
        .dec_byte_counter  (dec_byte_counter),
        .busy      (busy),
        .done      (done),
        .ack_error (ack_error),
        .byte_done (byte_done)
    );
endmodule

proyecto principal/I2C/TESTBENCH.v
`timescale 1ns / 1ps

module tb_TOP_I2C;

    localparam CLK_FREQ_HZ = 10_000_000;
    localparam I2C_FREQ_HZ = 1_000_000;
    localparam CLK_PERIOD  = 100; // 100ns

    reg        clk;
    reg        rst;
    reg        start;
    reg        rw;
    reg  [7:0] tx_byte;
    reg  [7:0] num_bytes;

    wire [7:0] rx_data;
    wire       busy;
    wire       done;
    wire       ack_error;
    wire       byte_done;

    tri1       SDA;
    wire       SCL;

    reg        slave_drive_low;
    reg  [7:0] bytes_enviados_master;
    reg  [7:0] bytes_recibidos_master;

    // Resistencias Pull-Up del bus
    assign SDA = slave_drive_low ? 1'b0 : 1'bz;

    pullup(SDA);

    // Instanciación de la Unidad Bajo Prueba (UUT)
    TOP_I2C #(
        .CLK_FREQ_HZ(CLK_FREQ_HZ),
        .I2C_FREQ_HZ(I2C_FREQ_HZ)
    ) uut (
        .clk(clk),
        .rst(rst),
        .start(start),
        .rw(rw),
        .tx_byte(tx_byte),
        .num_bytes(num_bytes),
        .rx_data(rx_data),
        .busy(busy),
        .done(done),
        .ack_error(ack_error),
        .byte_done(byte_done),
        .SDA(SDA),
        .SCL(SCL)
    );

    // Generador de Reloj del Sistema
    always #(CLK_PERIOD/2) clk = ~clk;

    task aplicar_reset;
        begin
            rst = 1; start = 0; rw = 0;
            tx_byte = 8'h00; num_bytes = 8'd0;
            slave_drive_low = 0;
            bytes_enviados_master = 0; bytes_recibidos_master = 0;
            #(CLK_PERIOD * 5);
            rst = 0;
            #(CLK_PERIOD * 2);
        end
    endtask

    // Modelo del Esclavo Emulado 

    integer bit_cnt;
    reg [7:0] frame_idx;
    reg [7:0] data_to_master;
    reg [7:0] shift_reg_esclavo;
    reg       slave_rw; // El esclavo guarda la dirección de flujo de forma autónoma

    // Reset de la transacción
    always @(posedge start or posedge rst) begin
        bit_cnt         <= 0;
        frame_idx       <= 0;
        slave_drive_low <= 0;
        slave_rw        <= 0;
    end

    // Muestreo de Datos Seguro: Siempre en el flanco de SUBIDA (SCL Alto = Dato Estable)
    always @(posedge SCL) begin
        if (busy) begin
            if (bit_cnt < 8) begin
                if (frame_idx == 0 || slave_rw == 0) begin
                    shift_reg_esclavo <= {shift_reg_esclavo[6:0], SDA};
                end
            end
            bit_cnt <= bit_cnt + 1;
        end
    end

    // Control del Bus y Respuestas: En el flanco de BAJADA (SCL Bajo = Permitido cambiar SDA)
    always @(negedge SCL) begin
        if (busy) begin
            if (bit_cnt == 8) begin
                // Fin del ciclo de transmisión de datos, flanco previo al ACK (9no pulso)
                if (frame_idx == 0) begin : FRAME_DIRECCION
                    slave_drive_low <= 1; // Responder con ACK
                    slave_rw        <= shift_reg_esclavo[0]; // El bit de dirección real (Bit 0)
                    $display("[TB - Esclavo] Direccion detectada: 0x%h. Modo seteado por Bus: %s", shift_reg_esclavo, shift_reg_esclavo[0] ? "LECTURA" : "ESCRITURA");
                end
                else if (slave_rw == 0) begin : FRAME_ESCRITURA
                    slave_drive_low <= 1; // Responder con ACK al maestro
                    $display("[TB - Esclavo] Recibido byte %0d del Maestro (Valor: 0x%h). Respondiendo con ACK.", bytes_enviados_master + 1, shift_reg_esclavo);
                end
                else begin : FRAME_LECTURA_ACK
                    slave_drive_low <= 0; // El maestro controla el ACK en modo lectura
                end
            end 
            else if (bit_cnt == 9) begin
                // Fin del ciclo de ACK, pasamos al siguiente frame
                bit_cnt         <= 0;
                frame_idx       <= frame_idx + 1;
                
                if (slave_rw == 1) begin
                    data_to_master = (frame_idx + 1 == 1) ? 8'hAB : 8'hCD;
                    slave_drive_low <= ~data_to_master[7];
                end else begin
                    slave_drive_low <= 0;
                end
            end
            else begin
                // Transmisión de los bits restantes (Bit 6 al Bit 0) en modo lectura
                if (slave_rw == 1 && frame_idx > 0) begin
                    if (bit_cnt < 8) begin
                        data_to_master = (frame_idx == 1) ? 8'hAB : 8'hCD;
                        slave_drive_low <= ~data_to_master[7 - bit_cnt];
                    end
                end else begin
                    slave_drive_low <= 0;
                end
            end
        end
    end

    // Contadores estadísticos del Testbench (Ajustado a bit_cnt == 8 debido al nuevo muestreo)
    always @(negedge SCL) begin
        if (busy && bit_cnt == 8) begin
            if (frame_idx != 0) begin
                if (slave_rw == 0) bytes_enviados_master   <= bytes_enviados_master + 1;
                else               bytes_recibidos_master  <= bytes_recibidos_master + 1;
            end
        end
    end

    // Estímulos de Prueba

    initial begin
        $dumpfile("tb_TOP_I2C.vcd");
        $dumpvars(0, tb_TOP_I2C);

        clk = 0;
        aplicar_reset();

        // PRUEBA 1: ESCRITURA DE 2 BYTES DE DATOS

        $display("\n--- Iniciando Transaccion de Escritura (2 Bytes de Datos) ---");

        num_bytes = 8'd3;      // Exactamente 2 bytes de datos
        rw        = 1'b0;      // Operación de escritura
        tx_byte   = 8'h3E;     // Byte de dirección (Bit 0 en '0' para escritura)
        start     = 1'b1;
        #(CLK_PERIOD);
        start     = 1'b0;

        @(posedge byte_done);  
        #(CLK_PERIOD / 4);     // Retardo de seguridad para evitar condiciones de carrera (Setup Time)
        tx_byte   = 8'h11;     
        $display("[TB] Direccion procesada de forma segura. Cargando dato 1: 0x11");

        @(posedge byte_done);  
        #(CLK_PERIOD / 4);     
        tx_byte   = 8'hA5;     
        $display("[TB] Dato 1 procesado de forma segura. Cargando dato 2: 0xA5");

        @(posedge done);
        $display("[TB] Transaccion de Escritura Finalizada de forma exitosa.");
        #(CLK_PERIOD * 20);

        // PRUEBA 2: LECTURA DE 2 BYTES DE DATOS

        $display("\n--- Iniciando Transaccion de Lectura (2 Bytes de Datos) ---");
        bytes_recibidos_master = 0;

        num_bytes = 8'd3;      // Se esperan exactamente 2 bytes
        rw        = 1'b1;      // Operación de lectura
        tx_byte   = 8'h3F;     // Byte de dirección (Bit 0 en '1' para lectura)
        start     = 1'b1;
        #(CLK_PERIOD);
        start     = 1'b0;

        @(posedge byte_done);  
        $display("[TB] Direccion de lectura validada.");

        @(posedge byte_done);  
        $display("[TB] Maestro capto el 1er Byte. Valor: 0x%H (Esperado: 0xAB)", rx_data);

        // El segundo byte provocará la activación de done directo debido al fin del conteo.
        @(posedge done);
        $display("[TB] Maestro capto el 2do Byte. Valor: 0x%H (Esperado: 0xCD)", rx_data);
        $display("[TB] Transaccion de Lectura Finalizada.");

        #(CLK_PERIOD * 20);
        $display("\n--- Todas las pruebas terminaron satisfactoriamente ---");
        $finish;
    end

endmodule

proyecto principal/controlador ads1115/I2C/tb_TOP_I2C.vcd
$date
	Thu Jul  9 17:48:17 2026
$end
$version
	Icarus Verilog
$end
$timescale
	1ps
$end
$scope module tb_TOP_I2C $end
$var wire 1 ! SDA $end
$var wire 8 " rx_data [7:0] $end
$var wire 1 # done $end
$var wire 1 $ byte_done $end
$var wire 1 % busy $end
$var wire 1 & ack_error $end
$var wire 1 ' SCL $end
$var parameter 32 ( CLK_FREQ_HZ $end
$var parameter 32 ) CLK_PERIOD $end
$var parameter 32 * I2C_FREQ_HZ $end
$var reg 8 + bytes_enviados_master [7:0] $end
$var reg 8 , bytes_recibidos_master [7:0] $end
$var reg 1 - clk $end
$var reg 8 . data_to_master [7:0] $end
$var reg 8 / frame_idx [7:0] $end
$var reg 8 0 num_bytes [7:0] $end
$var reg 1 1 rst $end
$var reg 1 2 rw $end
$var reg 8 3 shift_reg_esclavo [7:0] $end
$var reg 1 4 slave_drive_low $end
$var reg 1 5 slave_rw $end
$var reg 1 6 start $end
$var reg 8 7 tx_byte [7:0] $end
$var integer 32 8 bit_cnt [31:0] $end
$scope module uut $end
$var wire 1 ! SDA $end
$var wire 1 - clk $end
$var wire 8 9 num_bytes [7:0] $end
$var wire 1 1 rst $end
$var wire 1 2 rw $end
$var wire 1 : sda_in $end
$var wire 1 6 start $end
$var wire 8 ; tx_byte [7:0] $end
$var wire 1 < z_bytes $end
$var wire 1 = z_bits $end
$var wire 1 > tx_bit $end
$var wire 1 ? store_rx $end
$var wire 1 @ shift_tx $end
$var wire 1 A shift_rx $end
$var wire 1 B sda_pull_low $end
$var wire 1 C sda_mux_sel $end
$var wire 1 D sda_force_low $end
$var wire 1 E scl_rise $end
$var wire 1 F scl_internal $end
$var wire 1 G scl_fall $end
$var wire 1 H scl_enable $end
$var wire 8 I rx_data [7:0] $end
$var wire 1 J load_shift $end
$var wire 1 K load_byte_counter $end
$var wire 1 L load_bit_counter $end
$var wire 1 # done $end
$var wire 1 M dec_byte_counter $end
$var wire 1 N dec_bit_counter $end
$var wire 8 O byte_value [7:0] $end
$var wire 1 $ byte_done $end
$var wire 1 % busy $end
$var wire 3 P bit_value [2:0] $end
$var wire 1 & ack_error $end
$var wire 1 ' SCL $end
$var parameter 32 Q CLK_FREQ_HZ $end
$var parameter 32 R I2C_FREQ_HZ $end
$var reg 1 S sda_meta $end
$var reg 1 T sda_sync $end
$scope module BIT_COUNTER $end
$var wire 1 - clk $end
$var wire 1 1 rst $end
$var wire 3 U value [2:0] $end
$var wire 1 = z_bits $end
$var wire 1 L load $end
$var wire 1 N dec $end
$var reg 3 V count [2:0] $end
$upscope $end
$scope module BYTE_COUNTER $end
$var wire 1 - clk $end
$var wire 8 W num_bytes [7:0] $end
$var wire 1 1 rst $end
$var wire 8 X value [7:0] $end
$var wire 1 < z_bytes $end
$var wire 1 K load $end
$var wire 1 M dec $end
$var reg 8 Y count [7:0] $end
$upscope $end
$scope module CLOCK_GEN $end
$var wire 1 - clk $end
$var wire 1 1 rst $end
$var wire 1 H enable $end
$var parameter 32 Z CLK_FREQ_HZ $end
$var parameter 32 [ COUNTER_WIDTH $end
$var parameter 64 \ HALF_PERIOD $end
$var parameter 32 ] I2C_FREQ_HZ $end
$var reg 3 ^ counter [2:0] $end
$var reg 1 F scl $end
$var reg 1 G scl_fall $end
$var reg 1 E scl_rise $end
$upscope $end
$scope module CONTROL $end
$var wire 8 _ byte_value [7:0] $end
$var wire 1 - clk $end
$var wire 1 1 rst $end
$var wire 1 2 rw $end
$var wire 1 G scl_fall $end
$var wire 1 E scl_rise $end
$var wire 1 : sda_in $end
$var wire 1 6 start $end
$var wire 1 = z_bits $end
$var wire 1 < z_bytes $end
$var parameter 10 ` S_BYTE_DONE $end
$var parameter 10 a S_DONE $end
$var parameter 10 b S_IDLE $end
$var parameter 10 c S_RX_ACK $end
$var parameter 10 d S_RX_DATA $end
$var parameter 10 e S_START $end
$var parameter 10 f S_STOP $end
$var parameter 10 g S_STOP_WAIT $end
$var parameter 10 h S_TX_ACK $end
$var parameter 10 i S_TX_DATA $end
$var reg 10 j NEXT_STATE [9:0] $end
$var reg 1 & ack_error $end
$var reg 1 % busy $end
$var reg 1 $ byte_done $end
$var reg 1 N dec_bit_counter $end
$var reg 1 M dec_byte_counter $end
$var reg 8 k delay_cnt [7:0] $end
$var reg 1 # done $end
$var reg 1 L load_bit_counter $end
$var reg 1 K load_byte_counter $end
$var reg 1 J load_shift $end
$var reg 1 H scl_enable $end
$var reg 1 D sda_force_low $end
$var reg 1 C sda_mux_sel $end
$var reg 1 A shift_rx $end
$var reg 1 @ shift_tx $end
$var reg 1 ? store_rx $end
$upscope $end
$scope module SHIFT $end
$var wire 1 - clk $end
$var wire 1 J load $end
$var wire 1 1 rst $end
$var wire 8 l rx_data [7:0] $end
$var wire 1 : sda_in $end
$var wire 1 A shift_rx $end
$var wire 1 @ shift_tx $end
$var wire 1 ? store_rx $end
$var wire 8 m tx_byte [7:0] $end
$var wire 1 > tx_bit $end
$var reg 8 n rx_reg [7:0] $end
$var reg 8 o shift_reg [7:0] $end
$upscope $end
$upscope $end
$scope begin FRAME_DIRECCION $end
$upscope $end
$scope begin FRAME_ESCRITURA $end
$upscope $end
$scope begin FRAME_LECTURA_ACK $end
$upscope $end
$scope task aplicar_reset $end
$upscope $end
$upscope $end
$enddefinitions $end
$comment Show the parameter values. $end
$dumpall
b100 i
b100000 h
b100000000 g
b10000000 f
b10 e
b10000 d
b1000 c
b1 b
b1000000000 a
b1000000 `
b11110100001001000000 ]
b101 \
b11 [
b100110001001011010000000 Z
b11110100001001000000 R
b100110001001011010000000 Q
b11110100001001000000 *
b1100100 )
b100110001001011010000000 (
$end
#0
$dumpvars
b0 o
b0 n
b0 m
b0 l
b0 k
b1 j
b0 _
b0 ^
b0 Y
b0 X
b0 W
b0 V
b0 U
1T
1S
b0 P
b0 O
0N
0M
0L
0K
0J
b0 I
0H
0G
1F
0E
0D
1C
0B
0A
0@
0?
0>
1=
1<
b0 ;
1:
b0 9
b0 8
b0 7
06
05
04
bx 3
02
11
b0 0
b0 /
bx .
0-
b0 ,
b0 +
z'
0&
0%
0$
0#
b0 "
1!
$end
#50000
1-
#100000
0-
#150000
1-
#200000
0-
#250000
1-
#300000
0-
#350000
1-
#400000
0-
#450000
1-
#500000
0-
01
#550000
1-
#600000
0-
#650000
1-
#700000
0-
16
b111110 7
b111110 ;
b111110 m
b11 0
b11 9
b11 W
#750000
0!
1B
1%
1J
1K
1D
1L
1H
b10 j
1-
#800000
0-
06
#850000
0S
0<
b11 O
b11 X
b11 _
b11 Y
0=
b111 P
b111 U
b111 V
b111110 o
b1 ^
1-
#900000
0-
#950000
b10 ^
0:
0T
1-
#1000000
0-
#1050000
b11 ^
1-
#1100000
0-
#1150000
b100 ^
1-
#1200000
0-
#1250000
0'
1G
0F
b0 ^
1-
#1300000
0-
#1350000
0J
0K
0D
0C
0L
0G
b1 ^
b100 j
1-
#1400000
0-
#1450000
b10 ^
1-
#1500000
0-
#1550000
b11 ^
1-
#1600000
0-
#1650000
b100 ^
1-
#1700000
0-
#1750000
b1 8
bx0 3
z'
1E
1F
b0 ^
1-
#1800000
0-
#1850000
0E
b1 ^
1-
#1900000
0-
#1950000
b10 ^
1-
#2000000
0-
#2050000
b11 ^
1-
#2100000
0-
#2150000
b100 ^
1-
#2200000
0-
#2250000
1@
1N
0'
1G
0F
b0 ^
1-
#2300000
0-
#2350000
0@
0N
0G
b1 ^
b1111100 o
b110 P
b110 U
b110 V
1-
#2400000
0-
#2450000
b10 ^
1-
#2500000
0-
#2550000
b11 ^
1-
#2600000
0-
#2650000
b100 ^
1-
#2700000
0-
#2750000
b10 8
bx00 3
z'
1E
1F
b0 ^
1-
#2800000
0-
#2850000
0E
b1 ^
1-
#2900000
0-
#2950000
b10 ^
1-
#3000000
0-
#3050000
b11 ^
1-
#3100000
0-
#3150000
b100 ^
1-
#3200000
0-
#3250000
1@
1N
0'
1G
0F
b0 ^
1-
#3300000
0-
#3350000
1!
0B
0@
0N
1>
0G
b1 ^
b11111000 o
b101 P
b101 U
b101 V
1-
#3400000
0-
#3450000
1S
b10 ^
1-
#3500000
0-
#3550000
b11 ^
1:
1T
1-
#3600000
0-
#3650000
b100 ^
1-
#3700000
0-
#3750000
b11 8
bx001 3
z'
1E
1F
b0 ^
1-
#3800000
0-
#3850000
0E
b1 ^
1-
#3900000
0-
#3950000
b10 ^
1-
#4000000
0-
#4050000
b11 ^
1-
#4100000
0-
#4150000
b100 ^
1-
#4200000
0-
#4250000
1@
1N
0'
1G
0F
b0 ^
1-
#4300000
0-
#4350000
0@
0N
0G
b1 ^
b11110000 o
b100 P
b100 U
b100 V
1-
#4400000
0-
#4450000
b10 ^
1-
#4500000
0-
#4550000
b11 ^
1-
#4600000
0-
#4650000
b100 ^
1-
#4700000
0-
#4750000
b100 8
bx0011 3
z'
1E
1F
b0 ^
1-
#4800000
0-
#4850000
0E
b1 ^
1-
#4900000
0-
#4950000
b10 ^
1-
#5000000
0-
#5050000
b11 ^
1-
#5100000
0-
#5150000
b100 ^
1-
#5200000
0-
#5250000
1@
1N
0'
1G
0F
b0 ^
1-
#5300000
0-
