calculadora/rtl/cores/Multiplicador/Control_Multiplicador.v
module Control_Multiplicador(
    
    input clk,
    input init,
    input Z,
    input LSB,

    output reg ADD,
    output reg SH,
    output reg DEC,
    output reg LD,
    output reg DONE

);

// DEFINICIÓN DE ESTADOS

    parameter S_START     = 3'b000;
    parameter S_CHECK     = 3'b001;
    parameter S_ADD       = 3'b010;
    parameter S_SHIFT     = 3'b011;
    parameter S_END       = 3'b100;

    reg [2:0] NEXT_STATE;
    reg [5:0] COUNT;

// MAQUINA DE ESTADOS

    always @(posedge clk) begin

        case (NEXT_STATE)
        
            S_START: begin
                COUNT = 0;
                if (init) NEXT_STATE = S_CHECK;
                else      NEXT_STATE = S_START;
            end
            
            S_CHECK: begin
                if (Z)    NEXT_STATE = S_END;
                if (LSB)  NEXT_STATE = S_ADD;
                else      NEXT_STATE = S_SHIFT;
                
            end

            S_ADD: begin
                NEXT_STATE = S_SHIFT;
            end

            S_SHIFT: begin
                if (Z)    NEXT_STATE = S_END;
                else      NEXT_STATE = S_CHECK;
                
            end

            S_END: begin
                COUNT = COUNT + 1;
                NEXT_STATE = (COUNT>30) ? S_START : S_END; // contador para alargar la señal DONE, esto para que el procesador le de tiempo de leer.
            end
                    
            default: NEXT_STATE = S_START;

        endcase
    end

// LOGICA DE SALIDAS

    always @(*) begin 
        case (NEXT_STATE)
        
            S_START: begin
                ADD   = 0;
                SH    = 0;
                DEC   = 0;
                LD    = 1;
                DONE  = 0;
            end
        
            S_CHECK: begin
                ADD   = 0;
                SH    = 0;
                DEC   = 0;
                LD    = 0;
                DONE  = 0;
            end     

            S_ADD: begin
                ADD   = 1;
                SH    = 0;
                DEC   = 0;
                LD    = 0;
                DONE  = 0;
            end

            S_SHIFT: begin
                ADD   = 0;
                SH    = 1;
                DEC   = 1;
                LD    = 0;
                DONE  = 0;
            end      

            S_END: begin
                ADD   = 0;
                SH    = 0;
                DEC   = 0;
                LD    = 0;
                DONE  = 1;
            end

            default: begin
                ADD   = 0;
                SH    = 0;
                DEC   = 0;
                LD    = 0;
                DONE  = 0;
            end

        endcase
    end

endmodule

calculadora/rtl/cores/Multiplicador/Contador_Multiplicador.v
module contador_Multiplicador
(
    input   clk,    
    input   reset,  
    input   in,
  
    output  reg [4:0] out,
    output  zero 
);
    always @(posedge clk) begin //logica secuencial en flanco de subida 

        if(reset)
            out <= 5'd16;
        else if(in)
            out <= out - 1;
    end
    
    assign zero = (out == 0) ? 1 : 0; 

endmodule

calculadora/rtl/cores/Multiplicador/Acumulador_Multiplicador.v
module Acumulador_Multiplicador(

    input clk,
    input LD,                     
    input ADD,                    
    input SH,                     
    input signed [31:0] A_long,   

    output reg signed [31:0] ACC, 
    output ACC_LSB                
);

// bit que entra a B_long en shift
assign ACC_LSB = ACC[0];

always @(posedge clk) begin

    if(LD)
        ACC <= 32'd0;

    else if(ADD)
        ACC <= ACC + A_long;

    else if(SH)
        ACC <= ACC >>> 1;   // shift aritmético (guarda el signo)

end

endmodule

calculadora/rtl/cores/Multiplicador/B_long_Multiplicador.v
module B_long_Multiplicador(

    input clk,
    input LD,
    input SH,
    input ACC_LSB,   
    input signed [15:0] B,
 
    output reg signed [31:0] B_long,
    output LSB
);

    assign LSB = B_long[0];

    always @(posedge clk) begin
        if(LD)
            B_long <= {{16{B[15]}}, B};

        else if(SH)
        
        B_long <= {ACC_LSB, B_long[31:1]};
    end

endmodule

calculadora/rtl/cores/Multiplicador/A_long_Multiplicador.v
module A_long_Multiplicador(

    input clk,
    input LD,
    input signed [15:0] A,
    
    output reg signed [31:0] A_long
);

    always @(posedge clk) begin
        if(LD)
            A_long <= {{16{A[15]}}, A};
    end

endmodule

calculadora/rtl/cores/Multiplicador/TOP_Multiplicador.v
module TOP_Multiplicador (

    input reset,
    input clk,
    input init,

    input signed [15:0] Multiplicando,
    input signed [15:0] Multiplicador,
    
    output [31:0] Resultado,
    output DONE

);

assign Resultado = B_long;

wire signed [31:0] A_long;
wire signed [31:0] B_long;
wire signed [31:0] ACC;

wire W_LD;
wire W_SH;
wire W_ADD;
wire W_DEC;
wire W_LSB;
wire W_Z;

wire ACC_LSB;
wire [4:0] count;

A_long_Multiplicador A_long_reg (

    .clk(clk),
    .LD(W_LD),  
    .A(Multiplicando),

    .A_long(A_long)

);

B_long_Multiplicador B_long_reg(

    .clk(clk),
    .LD(W_LD),
    .SH(W_SH),
    .ACC_LSB(ACC_LSB),
    .B(Multiplicador),

    .B_long(B_long),
    .LSB(W_LSB)

);

Acumulador_Multiplicador ACC0(

    .clk(clk),
    .LD(W_LD),
    .ADD(W_ADD),
    .SH(W_SH),
    .A_long(A_long),

    .ACC(ACC),
    .ACC_LSB(ACC_LSB)

);

contador_Multiplicador contador_Multiplicador0(

    .clk(clk),
    .reset(W_LD),
    .in(W_DEC),

    .out(count),
    .zero(W_Z)
);

Control_Multiplicador Control_Multiplicador0(
    
    .clk(clk),
    .init(init),
    .Z(W_Z),
    .LSB(W_LSB),

    .ADD(W_ADD),
    .SH(W_SH),
    .DEC(W_DEC),
    .LD(W_LD),
    .DONE(DONE)
);

endmodule

calculadora/rtl/cores/Multiplicador/Testbench_Multiplicador.v
`timescale 1ns/1ps

module tb_TOP_Multiplicador;

reg clk;
reg reset;
reg init;

reg signed [15:0] Multiplicando;
reg signed [15:0] Multiplicador;

wire [31:0] Resultado;
wire DONE;

// --------instanciar--------
TOP_Multiplicador DUT(
    .reset(reset),
    .clk(clk),
    .init(init),
    .Multiplicando(Multiplicando),
    .Multiplicador(Multiplicador),
    .Resultado(Resultado),
    .DONE(DONE)
);

// -------- reloj 10ns --------
always #5 clk = ~clk;

// -------- simulación --------
initial begin

    // dump para GTKWave
    $dumpfile("multiplicador.vcd");

    clk = 0;
    reset = 0;
    init = 0;

    // valores iniciales
    Multiplicando = -100; 
    Multiplicador = 1000; 

    // reset inicial
    #10 reset = 1;
    #10 reset = 0;

    // iniciar multiplicación
    #10 init = 1;
    #10 init = 0;

    // esperar a que termine
    wait(DONE);

    #50 $finish;

end

// -------- monitor ciclo por ciclo --------
initial begin
    $display("--------------------------------------------------------------------------");
    $display("time | state señales internas");
    $display("--------------------------------------------------------------------------");

    $monitor(
        "t=%0t | LD=%b ADD=%b SH=%b DEC=%b | A_long=%b | B_long=%b | ACC=%b | count=%b | DONE=%b",
        $time,
        DUT.W_LD,
        DUT.W_ADD,
        DUT.W_SH,
        DUT.W_DEC,
        DUT.A_long,
        DUT.B_long,
        DUT.ACC,
        DUT.count,
        DONE
    );
end

endmodule

calculadora/rtl/cores/Multiplicador/multiplicador.vcd
$date
	Fri Feb 20 00:01:55 2026
$end
$version
	Icarus Verilog
$end
$timescale
	1ps
$end
$scope module tb_TOP_Multiplicador $end
$var wire 32 ! Resultado [31:0] $end
$var wire 1 " DONE $end
$var reg 16 # Multiplicador [15:0] $end
$var reg 16 $ Multiplicando [15:0] $end
$var reg 1 % clk $end
$var reg 1 & init $end
$var reg 1 ' reset $end
$scope module DUT $end
$var wire 16 ( Multiplicador [15:0] $end
$var wire 16 ) Multiplicando [15:0] $end
$var wire 32 * Resultado [31:0] $end
$var wire 1 % clk $end
$var wire 1 & init $end
$var wire 1 ' reset $end
$var wire 5 + count [4:0] $end
$var wire 1 , W_Z $end
$var wire 1 - W_SH $end
$var wire 1 . W_LSB $end
$var wire 1 / W_LD $end
$var wire 1 0 W_DEC $end
$var wire 1 1 W_ADD $end
$var wire 1 " DONE $end
$var wire 32 2 B_long [31:0] $end
$var wire 32 3 A_long [31:0] $end
$var wire 1 4 ACC_LSB $end
$var wire 32 5 ACC [31:0] $end
$scope module ACC0 $end
$var wire 1 % clk $end
$var wire 1 - SH $end
$var wire 1 / LD $end
$var wire 32 6 A_long [31:0] $end
$var wire 1 1 ADD $end
$var wire 1 4 ACC_LSB $end
$var reg 32 7 ACC [31:0] $end
$upscope $end
$scope module A_long_reg $end
$var wire 16 8 A [15:0] $end
$var wire 1 % clk $end
$var wire 1 / LD $end
$var reg 32 9 A_long [31:0] $end
$upscope $end
$scope module B_long_reg $end
$var wire 1 4 ACC_LSB $end
$var wire 16 : B [15:0] $end
$var wire 1 % clk $end
$var wire 1 - SH $end
$var wire 1 . LSB $end
$var wire 1 / LD $end
$var reg 32 ; B_long [31:0] $end
$upscope $end
$scope module Control_Multiplicador0 $end
$var wire 1 . LSB $end
$var wire 1 % clk $end
$var wire 1 & init $end
$var wire 1 , Z $end
$var parameter 3 < S_ADD $end
$var parameter 3 = S_CHECK $end
$var parameter 3 > S_END $end
$var parameter 3 ? S_SHIFT $end
$var parameter 3 @ S_START $end
$var reg 1 1 ADD $end
$var reg 6 A COUNT [5:0] $end
$var reg 1 0 DEC $end
$var reg 1 " DONE $end
$var reg 1 / LD $end
$var reg 3 B NEXT_STATE [2:0] $end
$var reg 1 - SH $end
$upscope $end
$scope module contador_Multiplicador0 $end
$var wire 1 % clk $end
$var wire 1 0 in $end
$var wire 1 / reset $end
$var wire 1 , zero $end
$var reg 5 C out [4:0] $end
$upscope $end
$upscope $end
$upscope $end
$enddefinitions $end
$comment Show the parameter values. $end
$dumpall
b0 @
b11 ?
b100 >
b1 =
b10 <
$end
#0
$dumpvars
bx C
bx B
bx A
bx ;
b1111101000 :
bx 9
b1111111110011100 8
bx 7
bx 6
bx 5
x4
bx 3
bx 2
x1
x0
x/
x.
x-
x,
bx +
bx *
b1111111110011100 )
b1111101000 (
0'
0&
0%
b1111111110011100 $
b1111101000 #
x"
bx !
$end
#5000
0"
1/
00
0-
01
b0 B
1%
#10000
0%
1'
#15000
0,
04
0.
b11111 +
b11111 C
b0 5
b0 7
b1111101000 !
b1111101000 *
b1111101000 2
b1111101000 ;
b11111111111111111111111110011100 3
b11111111111111111111111110011100 6
b11111111111111111111111110011100 9
1%
#20000
0%
0'
#25000
1%
#30000
0%
1&
#35000
0/
b1 B
1%
#40000
0%
0&
#45000
10
1-
b11 B
1%
#50000
0%
#55000
b11110 +
b11110 C
b111110100 !
b111110100 *
b111110100 2
b111110100 ;
00
0-
b1 B
1%
#60000
0%
#65000
10
1-
b11 B
1%
#70000
0%
#75000
b11101 +
b11101 C
b11111010 !
b11111010 *
b11111010 2
b11111010 ;
00
0-
b1 B
1%
#80000
0%
#85000
10
1-
b11 B
1%
#90000
0%
#95000
1.
b11100 +
b11100 C
b1111101 !
b1111101 *
b1111101 2
b1111101 ;
00
0-
b1 B
1%
#100000
0%
#105000
11
b10 B
1%
#110000
0%
#115000
b11111111111111111111111110011100 5
b11111111111111111111111110011100 7
10
1-
01
b11 B
1%
#120000
0%
#125000
0.
b111110 !
b111110 *
b111110 2
b111110 ;
b11111111111111111111111111001110 5
b11111111111111111111111111001110 7
b11011 +
b11011 C
00
0-
b1 B
1%
#130000
0%
#135000
10
1-
b11 B
1%
#140000
0%
#145000
1.
14
b11111 !
b11111 *
b11111 2
b11111 ;
b11111111111111111111111111100111 5
b11111111111111111111111111100111 7
b11010 +
b11010 C
00
0-
b1 B
1%
#150000
0%
#155000
11
b10 B
1%
#160000
0%
#165000
b11111111111111111111111110000011 5
b11111111111111111111111110000011 7
10
1-
01
b11 B
1%
#170000
0%
#175000
b11001 +
b11001 C
b11111111111111111111111111000001 5
b11111111111111111111111111000001 7
b10000000000000000000000000001111 !
b10000000000000000000000000001111 *
b10000000000000000000000000001111 2
b10000000000000000000000000001111 ;
00
0-
b1 B
1%
#180000
0%
#185000
11
b10 B
1%
#190000
0%
#195000
b11111111111111111111111101011101 5
b11111111111111111111111101011101 7
10
1-
01
b11 B
1%
#200000
0%
#205000
04
b11000000000000000000000000000111 !
b11000000000000000000000000000111 *
b11000000000000000000000000000111 2
b11000000000000000000000000000111 ;
b11111111111111111111111110101110 5
b11111111111111111111111110101110 7
b11000 +
b11000 C
00
0-
b1 B
1%
#210000
0%
#215000
11
b10 B
1%
#220000
0%
#225000
b11111111111111111111111101001010 5
b11111111111111111111111101001010 7
10
1-
01
b11 B
1%
#230000
0%
#235000
14
b10111 +
b10111 C
b11111111111111111111111110100101 5
b11111111111111111111111110100101 7
b1100000000000000000000000000011 !
b1100000000000000000000000000011 *
b1100000000000000000000000000011 2
b1100000000000000000000000000011 ;
00
0-
b1 B
1%
#240000
0%
#245000
11
b10 B
1%
#250000
0%
#255000
b11111111111111111111111101000001 5
b11111111111111111111111101000001 7
10
1-
01
b11 B
1%
#260000
0%
#265000
04
b10110000000000000000000000000001 !
b10110000000000000000000000000001 *
b10110000000000000000000000000001 2
b10110000000000000000000000000001 ;
b11111111111111111111111110100000 5
b11111111111111111111111110100000 7
b10110 +
b10110 C
00
0-
b1 B
1%
#270000
0%
#275000
11
b10 B
1%
#280000
0%
#285000
b11111111111111111111111100111100 5
b11111111111111111111111100111100 7
10
1-
01
b11 B
1%
#290000
0%
#295000
0.
b10101 +
b10101 C
b11111111111111111111111110011110 5
b11111111111111111111111110011110 7
b1011000000000000000000000000000 !
b1011000000000000000000000000000 *
b1011000000000000000000000000000 2
b1011000000000000000000000000000 ;
00
0-
b1 B
1%
#300000
0%
#305000
10
1-
b11 B
1%
#310000
0%
#315000
14
b10100 +
b10100 C
b11111111111111111111111111001111 5
b11111111111111111111111111001111 7
b101100000000000000000000000000 !
b101100000000000000000000000000 *
b101100000000000000000000000000 2
b101100000000000000000000000000 ;
00
0-
b1 B
1%
#320000
0%
#325000
10
1-
b11 B
1%
#330000
0%
#335000
b10011 +
b10011 C
b11111111111111111111111111100111 5
b11111111111111111111111111100111 7
b10010110000000000000000000000000 !
b10010110000000000000000000000000 *
b10010110000000000000000000000000 2
b10010110000000000000000000000000 ;
00
0-
b1 B
1%
#340000
0%
#345000
10
1-
b11 B
1%
#350000
0%
#355000
b10010 +
b10010 C
b11111111111111111111111111110011 5
b11111111111111111111111111110011 7
b11001011000000000000000000000000 !
b11001011000000000000000000000000 *
b11001011000000000000000000000000 2
b11001011000000000000000000000000 ;
00
0-
b1 B
1%
#360000
0%
#365000
10
1-
b11 B
1%
#370000
0%
#375000
b10001 +
b10001 C
b11111111111111111111111111111001 5
b11111111111111111111111111111001 7
b11100101100000000000000000000000 !
b11100101100000000000000000000000 *
b11100101100000000000000000000000 2
b11100101100000000000000000000000 ;
00
0-
b1 B
1%
#380000
0%
#385000
10
1-
b11 B
1%
#390000
0%
#395000
04
b10000 +
b10000 C
b11111111111111111111111111111100 5
b11111111111111111111111111111100 7
b11110010110000000000000000000000 !
b11110010110000000000000000000000 *
b11110010110000000000000000000000 2
b11110010110000000000000000000000 ;
00
0-
b1 B
1%
#400000
0%
#405000
10
1-
b11 B
1%
#410000
0%
#415000
b1111 +
b1111 C
b11111111111111111111111111111110 5
b11111111111111111111111111111110 7
b1111001011000000000000000000000 !
b1111001011000000000000000000000 *
b1111001011000000000000000000000 2
b1111001011000000000000000000000 ;
00
0-
b1 B
1%
#420000
0%
#425000
10
1-
b11 B
1%
#430000
0%
#435000
14
b1110 +
b1110 C
b11111111111111111111111111111111 5
b11111111111111111111111111111111 7
b111100101100000000000000000000 !
b111100101100000000000000000000 *
b111100101100000000000000000000 2
b111100101100000000000000000000 ;
00
0-
b1 B
1%
#440000
0%
#445000
10
1-
b11 B
1%
#450000
0%
#455000
b1101 +
b1101 C
b10011110010110000000000000000000 !
b10011110010110000000000000000000 *
b10011110010110000000000000000000 2
b10011110010110000000000000000000 ;
00
0-
b1 B
1%
#460000
0%
#465000
10
1-
b11 B
1%
#470000
0%
#475000
b1100 +
b1100 C
b11001111001011000000000000000000 !
b11001111001011000000000000000000 *
b11001111001011000000000000000000 2
b11001111001011000000000000000000 ;
00
0-
b1 B
1%
#480000
0%
#485000
10
1-
b11 B
1%
#490000
0%
#495000
b1011 +
b1011 C
b11100111100101100000000000000000 !
b11100111100101100000000000000000 *
b11100111100101100000000000000000 2
b11100111100101100000000000000000 ;
00
0-
b1 B
1%
#500000
0%
#505000
10
1-
b11 B
1%
#510000
0%
#515000
b1010 +
b1010 C
b11110011110010110000000000000000 !
b11110011110010110000000000000000 *
b11110011110010110000000000000000 2
b11110011110010110000000000000000 ;
00
0-
b1 B
1%
#520000
0%
#525000
10
1-
b11 B
1%
#530000
0%
#535000
b1001 +
b1001 C
b11111001111001011000000000000000 !
b11111001111001011000000000000000 *
b11111001111001011000000000000000 2
b11111001111001011000000000000000 ;
00
0-
b1 B
1%
#540000
0%
#545000
10
1-
b11 B
1%
#550000
0%
#555000
b1000 +
b1000 C
b11111100111100101100000000000000 !
b11111100111100101100000000000000 *
b11111100111100101100000000000000 2
b11111100111100101100000000000000 ;
00
0-
b1 B
1%
#560000
0%
#565000
10
1-
b11 B
1%
#570000
0%
#575000
b111 +
b111 C
b11111110011110010110000000000000 !
b11111110011110010110000000000000 *
b11111110011110010110000000000000 2
b11111110011110010110000000000000 ;
00
0-
b1 B
1%
#580000
0%
#585000
10
1-
b11 B
1%
#590000
0%
#595000
b110 +
b110 C
b11111111001111001011000000000000 !
b11111111001111001011000000000000 *
b11111111001111001011000000000000 2
b11111111001111001011000000000000 ;
00
0-
b1 B
1%
#600000
0%
#605000
10
1-
b11 B
1%
#610000
0%
#615000
b101 +
b101 C
b11111111100111100101100000000000 !
b11111111100111100101100000000000 *
b11111111100111100101100000000000 2
b11111111100111100101100000000000 ;
00
0-
b1 B
1%
#620000
0%
#625000
10
1-
b11 B
1%
#630000
0%
#635000
b100 +
b100 C
b11111111110011110010110000000000 !
b11111111110011110010110000000000 *
b11111111110011110010110000000000 2
b11111111110011110010110000000000 ;
00
0-
b1 B
1%
#640000
0%
#645000
10
1-
b11 B
1%
#650000
0%
#655000
b11 +
b11 C
b11111111111001111001011000000000 !
b11111111111001111001011000000000 *
b11111111111001111001011000000000 2
b11111111111001111001011000000000 ;
00
0-
b1 B
1%
#660000
0%
#665000
10
1-
b11 B
1%
#670000
0%
#675000
b10 +
b10 C
b11111111111100111100101100000000 !
b11111111111100111100101100000000 *
b11111111111100111100101100000000 2
b11111111111100111100101100000000 ;
00
0-
b1 B
1%
#680000
0%
#685000
10
1-
b11 B
1%
#690000
0%
#695000
b1 +
b1 C
b11111111111110011110010110000000 !
b11111111111110011110010110000000 *
b11111111111110011110010110000000 2
b11111111111110011110010110000000 ;
00
0-
b1 B
1%
#700000
0%
#705000
10
1-
b11 B
1%
#710000
0%
#715000
1,
b0 +
b0 C
b11111111111111001111001011000000 !
b11111111111111001111001011000000 *
b11111111111111001111001011000000 2
b11111111111111001111001011000000 ;
00
0-
b1 B
1%
#720000
0%
#725000
10
1-
b11 B
1%
#730000
0%
#735000
b11111111111111100111100101100000 !
b11111111111111100111100101100000 *
b11111111111111100111100101100000 2
b11111111111111100111100101100000 ;
1"
00
0-
b100 B
1%
#740000
0%
#745000
0"
bx00 B
1%
#750000
0%
#755000
1/
b0 B
1%
#760000
0%
#765000
0,
04
b1111101000 !
b1111101000 *
b1111101000 2
b1111101000 ;
b0 5
b0 7
b11111 +
b11111 C
1%
